{
    "0": "a man in a mask is looking at a door",
    "1": "a man in a hat is sitting in a room",
    "2": "a man in a military uniform is sitting on a bed",
    "3": "a soldier is sitting in a room with a light on",
    "4": "a soldier is sitting on a bed with a man",
    "5": "a soldier is sitting in a room with a man",
    "6": "a soldier is sitting in a room with a rifle",
    "7": "a soldier is lying down in a room with a gun",
    "8": "a soldier is lying down in a room with a rifle",
    "9": "a soldier is standing in a room with a rifle",
    "10": "a soldier is standing in a room with a rifle",
    "11": "a soldier is standing in a room with a gun",
    "12": "a soldier is standing in a room with a gun",
    "13": "a soldier is standing in a room with a rifle",
    "14": "a soldier is standing in a room with a gun",
    "15": "a soldier is standing in a room with a gun",
    "16": "a soldier is holding a gun in a room",
    "17": "a man is standing in a room with a gun",
    "18": "a soldier is standing in front of a door",
    "19": "a door with bullet holes in it",
    "20": "a door with bullet holes in it",
    "21": "a door with bullet holes in it",
    "22": "a door with bullet holes in it",
    "23": "a man is holding a broom in front of a door",
    "24": "a man holding a hammer in front of a door",
    "25": "a man is holding a hammer in front of a door",
    "26": "a soldier is holding a rifle in a doorway",
    "27": "a soldier is standing in a doorway with a rifle",
    "28": "a soldier is standing in a doorway",
    "29": "a soldier is standing in a doorway",
    "30": "a soldier is standing in a doorway",
    "31": "a soldier is standing in a hallway with a woman",
    "32": "a soldier in a military uniform is walking through a doorway",
    "33": "a soldier is standing in a doorway with a gun",
    "34": "a soldier is walking through a doorway",
    "35": "a soldier is standing in a doorway with a gun",
    "36": "a soldier is standing in a doorway with a gun",
    "37": "a soldier is standing in a doorway with a helmet",
    "38": "a soldier is looking at someone in a dark room",
    "39": "a soldier is looking at someone in a room",
    "40": "a soldier is standing in front of a door",
    "41": "a soldier is looking at a hole in the wall",
    "42": "a soldier is holding a gun in front of a wall",
    "43": "a soldier is holding a gun in front of a wall",
    "44": "a soldier is holding a rifle in front of a building",
    "45": "a soldier holding a rifle in front of a building",
    "46": "a soldier is holding a rifle in a dirty building",
    "47": "a soldier is holding a rifle in front of a building",
    "48": "two soldiers are holding guns in an old building",
    "49": "two soldiers are fighting in a building",
    "50": "two soldiers are fighting in a ruined building",
    "51": "a soldier holding a rifle in a dirty room",
    "52": "a soldier is holding a rifle in front of a wall",
    "53": "two soldiers are fighting in a building",
    "54": "a soldier holding a rifle in a doorway",
    "55": "two soldiers are fighting with a hammer",
    "56": "two soldiers are fighting in a ruined building",
    "57": "two soldiers in uniform are fighting in a building",
    "58": "two soldiers in uniform are fighting in a building",
    "59": "a soldier holding a rifle in front of a wall",
    "60": "a soldier holding a rifle in front of a wall",
    "61": "a soldier holding a rifle in front of a door",
    "62": "a soldier holding a rifle in a doorway",
    "63": "a soldier is holding a rifle in front of a wall",
    "64": "two soldiers in uniform are fighting in a building",
    "65": "two soldiers are holding a rifle in a dirty room",
    "66": "a soldier holding a rifle in a rusty building",
    "67": "a soldier holding a rifle in a dirty room",
    "68": "a soldier holding a rifle in a dirty room",
    "69": "a soldier holding a rifle in a dirty room",
    "70": "a soldier holding a rifle in a dirty room",
    "71": "two soldiers are holding a rifle in a dirty building",
    "72": "two soldiers are holding a rifle in a dirty building",
    "73": "a soldier holding a rifle in a dirty building",
    "74": "a soldier is holding a gun in his hand",
    "75": "a soldier is holding a gun in his hand",
    "76": "a soldier is holding a gun and looking at a hole",
    "77": "a soldier is looking at a hole in the wall",
    "78": "a soldier is leaning against a wall with his head",
    "79": "a soldier is leaning against a wall with his head on the ground",
    "80": "a soldier is leaning against a wall with a hole in it",
    "81": "a soldier is leaning against a wall with his head on the ground",
    "82": "a soldier is holding a gun while another man is looking at him",
    "83": "two soldiers are fighting in a building",
    "84": "two soldiers are fighting with a gun",
    "85": "two soldiers fighting with a rifle",
    "86": "two soldiers are fighting with a hammer",
    "87": "two soldiers are fighting with a gun",
    "88": "two soldiers are fighting with a gun",
    "89": "two soldiers are fighting in a building",
    "90": "two soldiers are fighting in a building",
    "91": "two soldiers are fighting in a building",
    "92": "two soldiers fighting in a building",
    "93": "two soldiers fighting in a building",
    "94": "two soldiers are fighting in a building",
    "95": "two soldiers fighting in a building",
    "96": "two soldiers fighting in a building",
    "97": "two soldiers fighting in a dirty room",
    "98": "two soldiers fighting with each other in a building",
    "99": "a soldier is holding a rifle against a wall",
    "100": "a soldier is holding a gun against a wall",
    "101": "two soldiers are fighting with a gun",
    "102": "a soldier is fighting with another soldier",
    "103": "a soldier is holding a gun while another man is holding a knife",
    "104": "a soldier is holding a knife in front of another soldier",
    "105": "a soldier is holding a rifle while another man is holding a gun",
    "106": "a soldier in uniform is holding a rifle",
    "107": "a soldier is holding a rifle while another man is holding a gun",
    "108": "a soldier holding a rifle in a building",
    "109": "a soldier is holding a rifle while another man is holding a gun",
    "110": "a soldier is holding a rifle while another man is holding a gun",
    "111": "a soldier is holding a rifle while another man is holding a gun",
    "112": "a soldier is holding a rifle while another man is holding a gun",
    "113": "a soldier holding a rifle in front of another soldier",
    "114": "a soldier holding a rifle while another man is holding a gun",
    "115": "a soldier holding a rifle while another man looks at him",
    "116": "a soldier is holding a gun while another man is holding a knife",
    "117": "a soldier is fighting with another soldier",
    "118": "a soldier is holding a rifle while another man is holding a gun",
    "119": "a soldier is hugging another soldier in a military uniform",
    "120": "a man in a hat is leaning against a wall",
    "121": "a soldier is holding a gun in front of a wall",
    "122": "a soldier is holding a rifle in front of a wall",
    "123": "a soldier is holding a gun while another man is holding a knife",
    "124": "a soldier is holding a gun while another man is holding a knife",
    "125": "a soldier is holding a gun while another man is holding a knife",
    "126": "a soldier is holding a gun while another man is holding a knife",
    "127": "a soldier is holding a gun while another man is holding a gun",
    "128": "a soldier is holding a gun while another man is holding a rifle",
    "129": "a soldier in a helmet is holding a rifle",
    "130": "a soldier is holding a rifle while another man is holding a gun",
    "131": "a soldier is holding a rifle in front of a wall",
    "132": "a soldier is holding a rifle while another man is looking at him",
    "133": "a soldier is looking at a wall with a rifle",
    "134": "a soldier is holding a rifle in front of a wall",
    "135": "a soldier is holding a gun in a dark room",
    "136": "a man is lying on the floor in a room with smoke",
    "137": "a man is lying on the floor in a room with smoke",
    "138": "a man is lying on the floor in a room with smoke",
    "139": "a man is lying on the floor in a room with smoke",
    "140": "a man is lying on the floor in a room with smoke",
    "141": "a man is lying on the floor in a room with smoke",
    "142": "a man is lying on the floor in a dark room",
    "143": "a man is lying on the floor in a room with smoke",
    "144": "a man is lying on the floor in a dark room",
    "145": "a man is lying on the floor in a dark room",
    "146": "a man is lying on the floor in a dark room",
    "147": "a man is lying on the floor in a room with smoke",
    "148": "a man is lying on the floor in a dark room",
    "149": "a man is lying on the floor in a dark room",
    "150": "a man is lying on the floor in a dark room",
    "151": "a man is lying on the floor in a room with smoke",
    "152": "a man is lying on the floor in a dark room",
    "153": "a man is lying on the floor in a room with smoke",
    "154": "a man is lying on the floor in a room with smoke",
    "155": "a man is lying on the floor in a dark room",
    "156": "a man is lying on the floor in a dark room",
    "157": "a man laying on the floor in a room with smoke",
    "158": "a man is lying on the ground in a room with smoke",
    "159": "a man is lying on the ground in a dark room",
    "160": "a man laying on the ground in a dark room",
    "161": "a man laying on the ground in a dark room",
    "162": "a man is lying on the floor in a dark room",
    "163": "a man is lying on the ground in a dark room",
    "164": "a man is lying on the floor in a dark room",
    "165": "a man is lying on the floor in a dark room",
    "166": "a man is lying on the ground in a dark room",
    "167": "a man laying on the ground in a dark room",
    "168": "a man is lying on the floor in a room",
    "169": "a man is lying on the floor in a room",
    "170": "a man is lying on the floor in a room with smoke",
    "171": "a man is lying on the floor in a room with smoke",
    "172": "a man is lying on the floor in a dark room",
    "173": "a man is lying on the floor in a dark room",
    "174": "a soldier is lying on the floor in a room",
    "175": "a man is lying on the floor in a room",
    "176": "a man is lying on the ground in a room",
    "177": "a man is lying on the floor in a room",
    "178": "a soldier is lying on the ground in a dark room",
    "179": "a man is lying on the floor in a room",
    "180": "a soldier is lying on the floor in a room",
    "181": "a man in a room with a man on the floor",
    "182": "a man is lying on the floor in a room",
    "183": "a man is lying on the floor in a room",
    "184": "a soldier is lying on the floor in a dark room",
    "185": "a soldier is lying on the floor in a room",
    "186": "a soldier is lying on the floor in a room",
    "187": "a man in a room with a gun and a man on the floor",
    "188": "a man is lying on the floor in a dark room",
    "189": "a man is lying on the floor in a dark room",
    "190": "a man is lying on the floor in a dark room",
    "191": "a man is lying on the floor in a room",
    "192": "a man is lying on the floor in a room",
    "193": "a man is lying on the floor in a room",
    "194": "a man is lying on the floor in a room",
    "195": "a man is lying on the floor in a room",
    "196": "a man is lying on the floor in a room",
    "197": "a man is lying on the floor in a room",
    "198": "a soldier is lying on the floor in a room",
    "199": "a man in a suit is standing in a room",
    "200": "a man is lying on the floor in a room",
    "201": "a man is lying on the floor in a room",
    "202": "a man is lying down in a room with a man",
    "203": "a man is lying down in a room with a man on top of him",
    "204": "a man is lying on the floor in a room",
    "205": "a man is lying on the floor in a room",
    "206": "a man is lying on the floor in a room",
    "207": "a man is lying on the floor in a room",
    "208": "a man is lying down in a room with a door",
    "209": "a man is lying down in a room with a man on top of him",
    "210": "a man is lying on the floor in a room",
    "211": "a man is lying down in a room with a broken door",
    "212": "a man is lying down in a room with a lot of debris",
    "213": "a man is lying on the floor in a dark room",
    "214": "a man is lying on the floor in a room",
    "215": "a man is lying on the floor in a room",
    "216": "a man is lying on the floor in a room",
    "217": "a man is lying on the floor in a dark room",
    "218": "a man is lying down in a room with a door",
    "219": "a man is lying down in a room with a gun",
    "220": "a man is lying down in a room with a fire",
    "221": "a man is lying on the floor in a room",
    "222": "a soldier is lying on the floor in a dark room",
    "223": "a man is lying on the floor in a dark room",
    "224": "a man is lying on the floor in a room",
    "225": "a man laying on the floor in a room with a gun",
    "226": "a soldier laying on the floor in a room",
    "227": "a soldier lying on the floor in a room",
    "228": "a man is lying on the floor in a room",
    "229": "a soldier is lying on the floor in a room",
    "230": "a soldier is lying on the floor in a room",
    "231": "a man is lying on the floor in a room",
    "232": "a man is lying on the floor in a room",
    "233": "a soldier is lying on the floor in a room",
    "234": "a soldier is lying on the floor in a room",
    "235": "a man laying on the floor in a room",
    "236": "a soldier is lying on the floor in a room",
    "237": "a soldier is lying on the floor in a room",
    "238": "a soldier is lying on the floor in a room",
    "239": "a soldier is lying on the floor in a room",
    "240": "a soldier is holding a gun in a dirty room",
    "241": "a soldier is holding a rifle in a room",
    "242": "a soldier is holding a rifle in a room",
    "243": "two soldiers are standing in a doorway with a rifle",
    "244": "a soldier is standing in a room with a gun",
    "245": "a soldier is standing in a room with a door",
    "246": "two soldiers in a room with a door",
    "247": "a soldier is standing in a room with a rifle",
    "248": "a soldier is holding a rifle in a hallway",
    "249": "a soldier is holding a rifle in a hallway",
    "250": "a man holding a rifle in a hallway",
    "251": "a man holding a rifle in a hallway",
    "252": "a man holding a rifle in a room",
    "253": "a soldier holding a rifle in a doorway",
    "254": "a man in a suit is holding a gun",
    "255": "a man in a military uniform is standing in a doorway",
    "256": "a man in a military uniform is standing in a hallway",
    "257": "a soldier is standing in a hallway with his gun",
    "258": "a soldier is holding a rifle in a hallway",
    "259": "a soldier is holding a rifle in a hallway",
    "260": "a man in a military uniform is standing in a hallway",
    "261": "a man is holding a gun in a hallway",
    "262": "a man is holding a gun in a hallway",
    "263": "a man is standing in a hallway with a backpack",
    "264": "a man is standing in a hallway with a gun",
    "265": "a man in a black jacket is standing in a hallway",
    "266": "a man is standing in a hallway with a gun",
    "267": "a man is hugging a woman in a hallway",
    "268": "two men are standing in a hallway with a gun",
    "269": "two men are standing in a doorway with a gun",
    "270": "a man is hugging a woman in a hallway",
    "271": "a man is standing in a hallway with a picture on the wall",
    "272": "a man is standing in a hallway with a picture on the wall",
    "273": "a man is standing in a hallway with a picture on the wall",
    "274": "a man is standing in a room with a picture on the wall",
    "275": "a man is walking down a hallway with a gun",
    "276": "a man is standing in a hallway with a gun",
    "277": "a man is holding a knife in a hallway",
    "278": "a man is standing in a room with a camera",
    "279": "a man is standing in a room with a door",
    "280": "a man is walking down a hallway with his hands on his hips",
    "281": "a man is leaning over a railing in a dark room",
    "282": "a man is bending over in a dark room",
    "283": "a man is leaning over a woman in a dark room",
    "284": "a man is leaning over a woman in a dark room",
    "285": "a man is looking at his phone in the dark",
    "286": "a person is sitting in a dark room",
    "287": "a man is holding a cell phone",
    "288": "a person is looking at a phone",
    "289": "a person is standing in the dark with a cell phone",
    "290": "a black dog in the dark",
    "291": "a person is standing in the dark",
    "292": "a black cat is standing in the dark",
    "293": "a person is holding a cell phone in the dark",
    "294": "a person is holding a cell phone in the dark",
    "295": "a person is holding a cell phone in the dark",
    "296": "a person is holding a cell phone in the dark",
    "297": "a person is holding a cell phone in the dark",
    "298": "a person is holding a cell phone",
    "299": "a person is holding a cell phone",
    "300": "a person is holding a cell phone",
    "301": "a person is holding a cell phone",
    "302": "a man is holding a cell phone in the dark",
    "303": "a man is standing in front of a dark window",
    "304": "a man is kissing a woman in the dark",
    "305": "a man is holding a cell phone in his hand",
    "306": "a man is holding a phone in the dark",
    "307": "a man is hugging a woman in a dark room",
    "308": "a man is hugging a woman in a dark room",
    "309": "a man is hugging a woman in a room",
    "310": "a man is hugging a woman in a dark room",
    "311": "a man is hugging a woman in a dark room",
    "312": "a man is hugging a woman in a dark room",
    "313": "a man is hugging a woman in a dark room",
    "314": "a man is hugging a woman in a dark room",
    "315": "a man is kissing a woman in a dark room",
    "316": "a man is kissing a woman in a dark room",
    "317": "a man is kissing a woman in a dark room",
    "318": "a man is standing in a dark room with a woman",
    "319": "a man is standing in a dark room with a man",
    "320": "a man is standing in front of a door",
    "321": "a man is holding a gun in his hand",
    "322": "a man is holding a knife in his hand",
    "323": "a man is holding a man with blood on his face",
    "324": "a man is holding a dead body in his hand",
    "325": "a man is holding a knife in his hand",
    "326": "a man is holding a knife in a dark room",
    "327": "a man is holding a knife in a dark room",
    "328": "a man is holding a man with blood on his arm",
    "329": "a man is holding a knife in his hand",
    "330": "a man is holding a gun in his hand",
    "331": "a man is holding a gun in his hand",
    "332": "a man is holding a gun in his hand",
    "333": "a man is standing in front of a door",
    "334": "a man is holding a sword in his hand",
    "335": "a man is holding a sword in his hand",
    "336": "a man is holding a gun in his hand",
    "337": "a man is holding a gun in the dark",
    "338": "a man is holding a gun in the dark",
    "339": "a man is holding a gun in the dark",
    "340": "a man is holding a gun in a dark room",
    "341": "a man is holding a woman in a dark room",
    "342": "a man is kissing a woman in a dark room",
    "343": "a man is hugging another man in a dark room",
    "344": "a man is laying on a bed with a man",
    "345": "a man is laying on top of another man",
    "346": "a man is hugging another man in a room",
    "347": "a man is laying down on a bed with another man",
    "348": "a man is holding another man in a dark room",
    "349": "a man is laying on top of another man",
    "350": "a man is holding another man in a dark room",
    "351": "a man is holding another man in a dark room",
    "352": "a man in military gear is fighting with another man",
    "353": "a soldier is hugging another soldier in the dark",
    "354": "a man in military uniform is hugging another man",
    "355": "a soldier is hugging another soldier in a dark room",
    "356": "a man is holding his head in his hand",
    "357": "a man is laying on a bed with his head on his hand",
    "358": "a man is hugging a woman in a room",
    "359": "a man hugging another man in a room",
    "360": "two men hugging in a room with a window",
    "361": "a man is hugging another man in a room",
    "362": "two soldiers hugging each other in a dark room",
    "363": "a man in military uniform is hugging another man",
    "364": "a man in military uniform is hugging another man",
    "365": "two men in military uniforms hugging each other",
    "366": "a man is hugging another man in a room",
    "367": "a man is holding his head in his hands",
    "368": "a man in military uniform is hugging another man",
    "369": "a man is hugging another man in a room",
    "370": "a man is hugging another man in a room",
    "371": "a man is hugging another man in a dark room",
    "372": "a man is hugging a woman in a dark room",
    "373": "a man is laying on his back in a dark room",
    "374": "a man is laying on his back in a dark room",
    "375": "a man is laying on a bed with a woman",
    "376": "a man is laying on his back in a dark room",
    "377": "a man is laying on his back in a room",
    "378": "a man is laying on top of a bed",
    "379": "a man is laying on his back with his arms around his neck",
    "380": "a man is laying on top of another man",
    "381": "a man is laying on his back with his arms around him",
    "382": "a man is laying on top of another man",
    "383": "a man is laying on the floor with a woman",
    "384": "a man is laying on top of another man",
    "385": "a man is laying on top of another man",
    "386": "a man is laying on his back in a room",
    "387": "a man is laying down in a room with a blanket",
    "388": "a man is laying down on his back in a room",
    "389": "a man is lying on his back in a room",
    "390": "a man is lying on the floor with his arms around another man",
    "391": "a man is lying on his back in a room",
    "392": "a man is lying on his back in a room",
    "393": "a man is lying on the floor with his arms around another man",
    "394": "a man is laying on the floor with a man on top of him",
    "395": "a man is lying on the floor with a bag on his back",
    "396": "a man is lying on the floor with a backpack",
    "397": "a man is lying down on a bed with a man on his back",
    "398": "a man is fighting with another man in a room",
    "399": "a soldier is fighting with another soldier in a room",
    "400": "a man is fighting with another man in a dark room",
    "401": "a man is fighting with another man in a room",
    "402": "a man is fighting with another man in a room",
    "403": "a man is fighting with another man in a room",
    "404": "a man is laying on the ground with blood on his face",
    "405": "a soldier is laying on the ground with blood on his face",
    "406": "a man is laying on the ground with blood on his face",
    "407": "a soldier is laying on the ground with blood on his face",
    "408": "a man is lying on the floor with blood on his face",
    "409": "a man is laying on the floor with blood on his face",
    "410": "a man is laying on the floor with blood on his face",
    "411": "a man is laying on the floor with blood on his face",
    "412": "a man is laying on the ground with blood on his face",
    "413": "a man is lying on the ground with blood on his face",
    "414": "a man is laying on the floor with blood on his face",
    "415": "a man is laying on a bed with blood on his face",
    "416": "a man is holding a man with blood on his face",
    "417": "a man is being pushed by another man",
    "418": "a man is holding a man with blood on his face",
    "419": "a man is laying on the floor with blood on his face",
    "420": "a man is holding a man with blood on his face",
    "421": "a man is holding a man with blood on his face",
    "422": "a man is holding a man with blood on his face",
    "423": "a soldier is holding a man with blood on his face",
    "424": "a man is laying on the floor with blood on his face",
    "425": "a man is holding a man with blood on his face",
    "426": "a man is laying on the floor with blood on his face",
    "427": "a man is holding a man in a room",
    "428": "a man is holding a man with blood on his face",
    "429": "a man is holding a knife while another man is holding a knife",
    "430": "a man is holding a man with blood on his face",
    "431": "a man is holding a man in a room with blood on his face",
    "432": "a man is holding a man with blood on his face",
    "433": "a man is holding a man in a room",
    "434": "a man is holding a man with blood on his face",
    "435": "a man is holding a man with blood on his face",
    "436": "a man is laying on a bed with blood on his face",
    "437": "a man is laying on a bed with a man in front of him",
    "438": "a man is laying on the floor with blood on his face",
    "439": "a man is laying on the floor with blood on his face",
    "440": "a man is holding a man with blood on his face",
    "441": "a man is laying on the floor with blood on his face",
    "442": "a man is laying on the floor with blood on his face",
    "443": "a man is being pushed down by another man",
    "444": "a man is being attacked by another man",
    "445": "a man is being attacked by another man",
    "446": "a man is being attacked by another man",
    "447": "a man is being attacked by another man",
    "448": "a man is laying on the floor with blood on his face",
    "449": "a man is laying on top of a dead man",
    "450": "a man is laying on the floor with blood on his face",
    "451": "a man is holding a man in a room",
    "452": "a man in military gear is laying on a bed with a man",
    "453": "a man is laying on a bed with a man in front of him",
    "454": "a man is laying on the floor with blood on his face",
    "455": "a man is holding a man with blood on his face",
    "456": "a man is holding a man with blood on his face",
    "457": "a man is holding a man with blood on his face",
    "458": "a man is holding a man in a room with blood on his face",
    "459": "a man is holding a man in a room",
    "460": "a man is laying on top of a man with blood on his face",
    "461": "two men are fighting over a piece of meat",
    "462": "a man is holding a man in a room",
    "463": "a man is holding a man in a room",
    "464": "a man is holding a man in a room",
    "465": "a man is laying on a bed with a man on top of him",
    "466": "a man in military gear is laying on a bed",
    "467": "a man is holding a man in a room",
    "468": "a man is holding a man in a room",
    "469": "a man is laying on a bed with a man on top of him",
    "470": "a man is laying on a bed with another man",
    "471": "a man is holding a man in a room",
    "472": "two men in military uniforms are fighting in a room",
    "473": "a soldier is laying on the floor with a man",
    "474": "a soldier is laying on top of a bed",
    "475": "a man is laying on a bed with a man on top of him",
    "476": "a man is laying on a bed with a man on top of him",
    "477": "a man is laying on a bed with a man on top of him",
    "478": "a soldier is laying on a bed with a teddy bear",
    "479": "a soldier is laying on the floor with a man",
    "480": "a soldier is laying on the floor with a man",
    "481": "a soldier is laying down on the floor with a knife",
    "482": "a soldier is laying on the floor with blood on his hands",
    "483": "two soldiers are laying on the floor in a room",
    "484": "a group of soldiers laying on the floor",
    "485": "a group of soldiers laying on the floor",
    "486": "a group of soldiers laying on the floor",
    "487": "a group of soldiers laying on the floor",
    "488": "a group of soldiers laying on the floor",
    "489": "a group of soldiers are laying on the floor",
    "490": "two soldiers are laying on the floor in a room",
    "491": "three soldiers are laying on the floor in a room",
    "492": "a soldier is laying on the floor with another soldier",
    "493": "a group of soldiers laying on the floor in a dark room",
    "494": "a soldier laying on the floor with another soldier",
    "495": "a soldier is laying on the ground with another soldier",
    "496": "a group of soldiers laying on the floor in a dark room",
    "497": "a man is laying on the floor with blood on his face",
    "498": "a group of soldiers are laying on the floor",
    "499": "a soldier is laying on the ground with blood on his face",
    "500": "a group of soldiers are laying on the floor",
    "501": "a group of soldiers are laying on the floor",
    "502": "a group of soldiers are laying on the floor",
    "503": "a group of soldiers are laying on the ground",
    "504": "a group of men are laying on the floor in a room",
    "505": "a group of soldiers are laying on the ground",
    "506": "a man is laying on the ground with a dead man",
    "507": "a man is laying on the ground with another man",
    "508": "a man is laying on the floor with a dead man",
    "509": "a soldier is laying on the ground with another soldier",
    "510": "a man is laying on the floor with a man on top of him",
    "511": "a soldier is laying on the floor with another soldier",
    "512": "a man is lying on the floor with another man",
    "513": "a man is laying on the floor with another man",
    "514": "a man is laying on the floor with another man",
    "515": "a man is laying on the floor with a man on top of him",
    "516": "a man is laying on the floor with a dead man",
    "517": "two men are fighting in a room with a dead body",
    "518": "a man is lying on the floor in a room",
    "519": "a man is lying on the floor in a room",
    "520": "a man is lying on the floor in a room",
    "521": "a man is lying on the floor in a room",
    "522": "a man is lying on the floor in a room",
    "523": "a man is lying down in a room with a man",
    "524": "a man is lying on the floor in a room",
    "525": "a man is lying on the floor in a room",
    "526": "a man is lying on the floor in a room",
    "527": "a man is lying down in a room with a man",
    "528": "a man is lying on the floor in a room",
    "529": "a man is lying down in a room with a lot of debris",
    "530": "a man is lying down in a room with a gun",
    "531": "a man is lying down in a room with a man",
    "532": "a man is lying on the floor in a room",
    "533": "a man is lying on the floor in a room",
    "534": "a soldier is lying down in a room with a broken door",
    "535": "a soldier is lying on the floor in a room",
    "536": "a man is lying on the floor in a room",
    "537": "a soldier laying on the floor in a room",
    "538": "a soldier is lying on the ground in a room",
    "539": "a soldier is lying on the ground in a room",
    "540": "a soldier is lying on the floor with blood on his face",
    "541": "a man laying on the ground with blood on his face",
    "542": "a soldier laying on the ground with blood on his face",
    "543": "a soldier laying on the ground in a room with blood on it",
    "544": "a soldier laying on the floor with blood on his face",
    "545": "a soldier laying on the ground with blood on his face",
    "546": "a soldier is lying on the ground in a room",
    "547": "a soldier is lying on the ground with blood on his face",
    "548": "a soldier is lying on the ground with blood on his face",
    "549": "a soldier is lying on the ground with blood on his face",
    "550": "a soldier laying on the ground with blood on his face",
    "551": "a soldier is lying on the floor with blood on his face",
    "552": "a soldier is lying on the floor with blood on his face",
    "553": "a soldier laying on the floor with blood on his face",
    "554": "a soldier laying on the ground with blood on his face",
    "555": "a soldier laying on the ground with blood on his face",
    "556": "a soldier laying on the ground with blood on his face",
    "557": "a soldier laying on the floor with blood on his face",
    "558": "a soldier laying on the floor with blood on his face",
    "559": "a soldier laying on the floor with blood on his face",
    "560": "a soldier laying on the floor with blood on his face",
    "561": "a soldier laying on the floor with blood on his face",
    "562": "a soldier laying on the floor with blood on his face",
    "563": "a soldier laying on the floor with blood on his face",
    "564": "a soldier lying on the floor with blood on his face",
    "565": "a soldier laying on the floor with blood on his face",
    "566": "a soldier laying on the floor with blood on his face",
    "567": "a man laying on the floor with blood on his face",
    "568": "a man laying on the floor with blood on his face",
    "569": "a soldier laying on the floor with blood on his face",
    "570": "a soldier laying on the floor with blood on his face",
    "571": "a soldier laying on the floor with blood on his face",
    "572": "a soldier laying on the floor with blood on his head",
    "573": "a man laying on the floor with blood on his face",
    "574": "a soldier is laying on the floor with blood on his face",
    "575": "a soldier is lying on the floor with blood on his face",
    "576": "a soldier laying on the ground with blood on his face",
    "577": "a soldier laying on the floor with blood on his face",
    "578": "a soldier laying on the floor with blood on his face",
    "579": "a soldier laying on the floor with blood on his face",
    "580": "a soldier is lying on the floor with blood on his face",
    "581": "a soldier is lying on the floor with blood on his face",
    "582": "a soldier laying on the floor with blood on his face",
    "583": "a soldier laying on the floor with blood on his face",
    "584": "a soldier laying on the floor with blood on his face",
    "585": "a man laying on the floor with blood on his face",
    "586": "a soldier laying on the ground with blood on his face",
    "587": "a soldier laying on the floor with blood on his face",
    "588": "a soldier laying on the floor with blood on his face",
    "589": "a soldier laying on the floor with blood on his face",
    "590": "a soldier laying on the floor with blood on his face",
    "591": "a soldier laying on the floor with blood on his face",
    "592": "a soldier is lying on the floor with blood on his face",
    "593": "a soldier laying on the floor with blood on his face",
    "594": "a soldier laying on the floor with blood on his face",
    "595": "a soldier is lying on the floor with blood on his face",
    "596": "a soldier is laying on top of another soldier",
    "597": "a man in military uniform is laying on the floor",
    "598": "a man is laying on the ground with a man on top of him",
    "599": "a man is laying on the floor with another man",
    "600": "a man is lying down in a room with a man",
    "601": "a soldier is laying down on the floor with a man",
    "602": "a man is laying down on the floor with his hands on his head",
    "603": "a man is laying on his back in a room",
    "604": "a man in military gear is laying down on the floor",
    "605": "a soldier is laying down on his back in a room",
    "606": "a man in military uniform is holding a man in a room",
    "607": "a man in military uniform is hugging a woman",
    "608": "a man is hugging a woman in a room",
    "609": "two men in military uniforms hugging each other",
    "610": "a man is hugging a woman in a room",
    "611": "a man is hugging a woman in a room",
    "612": "a man is laying down on his back in a room",
    "613": "a man is laying on the floor with his hands on his face",
    "614": "a man is laying on the floor with his hands on his head",
    "615": "a man is laying on a bed with his hands on his face",
    "616": "a man is laying down with his head on his shoulder",
    "617": "a man and woman hugging in a dark room",
    "618": "a man is holding a woman in a dark room",
    "619": "a man and woman hugging in a dark room",
    "620": "a man is laying on the floor with his hands on his head",
    "621": "a man is laying on the floor with another man",
    "622": "a man is laying on a bed with his head on his shoulder",
    "623": "a man is laying on his back in a dark room",
    "624": "two men laying down in a room with a blanket",
    "625": "two men laying down in a dark room",
    "626": "two men laying down in a dark room",
    "627": "two men laying down in a dark room",
    "628": "a man laying down in a dark room",
    "629": "a man is laying down in the dark with his hands on his head",
    "630": "a man is lying down in the dark with his hands on his head",
    "631": "a man laying down in the dark with his hands on his face",
    "632": "a man laying on the ground with his hands on his head",
    "633": "a man is laying down in the dark",
    "634": "a man is laying down in the dark with his hands on his head",
    "635": "a man laying down in the dark with his hands on his head",
    "636": "a man laying down in the dark with his hands on his head",
    "637": "a man laying down in the dark with his hands on his head",
    "638": "a man laying down in the dark with his hands on his head",
    "639": "a man laying on the ground with his hands on his head",
    "640": "a man is laying on the floor with his hands on his head",
    "641": "a man is laying down in the dark with his hands on his head",
    "642": "a man is laying down in a dark room",
    "643": "a man is laying on the floor with his hands on his head",
    "644": "a man is laying down in a room with other people",
    "645": "a man is laying on the floor with his hands on his head",
    "646": "a man laying on the ground with his hands on his head",
    "647": "a man is laying on the floor with his hands on his head",
    "648": "a man is laying on the floor with his hands on his head",
    "649": "a man laying on the ground with his hands on his head",
    "650": "a man laying on the ground with his hands on his head",
    "651": "a man laying on the ground with his hands on his head",
    "652": "a man laying on the floor with his hands on his head",
    "653": "a man laying on the ground with his hands on his head",
    "654": "a man laying on the ground with his hands on his head",
    "655": "a man laying on the ground with his hands on his head",
    "656": "a man laying on the ground with his hands on his head",
    "657": "a man laying on the ground with his hands on his head",
    "658": "a soldier laying on the ground with his hands on his head",
    "659": "a man is lying on the ground with his hands on his head",
    "660": "a man is lying on the ground with his hands on his head",
    "661": "a man is lying on the ground with his hands on his face",
    "662": "a man is lying on the ground with his hands on his head",
    "663": "a man is lying on the ground with his hands on his mouth",
    "664": "a man is lying on the ground with his mouth open",
    "665": "a man laying on the ground with his hands on his head",
    "666": "a soldier laying down on the ground with his hands on his head",
    "667": "a man is lying down in the dark with his hands on his head",
    "668": "a man in military gear is laying down",
    "669": "a soldier is holding a gun in the dark",
    "670": "a man is holding a gun while sitting in a room",
    "671": "two people hugging each other in a dark room",
    "672": "a woman is hugging a man in the dark"
}