{
    "0": "a car is seen driving down the street",
    "1": "a car is seen driving down the street",
    "2": "a car is seen driving down the street",
    "3": "a motorcycle is seen driving down the street",
    "4": "a car is driving down the street in front of a tree",
    "5": "a car is driving down the street in front of a tree",
    "6": "a car is seen driving down the street",
    "7": "a car is seen driving down the street",
    "8": "a car is seen driving down the street",
    "9": "a car is seen driving down the street",
    "10": "a car is seen driving down the street",
    "11": "a car is seen on the street with smoke coming out of it",
    "12": "a car is seen on the street with smoke coming out of it",
    "13": "a car is seen driving down the street",
    "14": "a car is seen driving down the street",
    "15": "a car is seen on the street with smoke coming out of it",
    "16": "a car is seen on the street with smoke coming out of it",
    "17": "a car is seen on the street with smoke coming out of it",
    "18": "a car is seen on the street with smoke coming out of it",
    "19": "a car is seen driving down the street",
    "20": "a car is seen on the street with a dog in it",
    "21": "a car is seen on the street with smoke coming out of it",
    "22": "a car is seen on the street with smoke coming out of it",
    "23": "a car is being driven down the street",
    "24": "a car is seen on the street with smoke coming out of it",
    "25": "a car is being pushed into the street by a car",
    "26": "a car is seen driving down the street",
    "27": "a car is parked on the street with a car in front of it",
    "28": "a car is seen driving down the street",
    "29": "a car is seen driving down the street",
    "30": "a car is parked on the street and a man is walking",
    "31": "a car is being blown up by a car",
    "32": "a car is being blown up by a fire",
    "33": "a car is seen on the street with smoke coming out of it",
    "34": "a car is seen on the street with smoke coming out of it",
    "35": "a car is thrown into the street by a car",
    "36": "a car is thrown into the street by a car",
    "37": "a car is seen driving down the street with smoke coming out of it",
    "38": "a video of a car being thrown into the street",
    "39": "a video of a car being blown up by a car",
    "40": "a man is seen riding a motorcycle on the street",
    "41": "a car is being blown up by a fire",
    "42": "a man is seen riding a motorcycle on the street",
    "43": "a man is seen riding a motorcycle in the street",
    "44": "a man is seen riding a motorcycle in the street",
    "45": "a man is seen riding a motorcycle in the street",
    "46": "a man is seen riding a motorcycle in the street",
    "47": "a man is seen riding a motorcycle in the street",
    "48": "a car is thrown into the air by a car",
    "49": "a car is being blown up by a car",
    "50": "a car is seen driving down the street with smoke coming out of it",
    "51": "a car is seen driving down the street with smoke coming out of it",
    "52": "a car is being smashed into a tree",
    "53": "a car is being blown up by a car",
    "54": "a car is being smashed into a street",
    "55": "a car is being blown up by a fire",
    "56": "a car is being pushed into a street",
    "57": "a car is being pushed into the street by a car",
    "58": "a car is being pushed into a tree",
    "59": "a car is being pushed into a tree",
    "60": "a car is being pushed into a tree",
    "61": "a car is being pushed into the street by a car",
    "62": "a car is seen driving through a street with smoke coming out of it",
    "63": "a car is seen driving through a street with smoke",
    "64": "a car is seen driving through a street with smoke",
    "65": "a car is seen driving through a street with smoke",
    "66": "a car is seen driving through a street with smoke",
    "67": "a car is seen driving through a street with smoke",
    "68": "a car is seen driving through the street with smoke",
    "69": "a car is being pushed into the street by a car",
    "70": "a car is seen driving down the street with a lot of dust",
    "71": "a car is seen driving down the street with a lot of dust",
    "72": "a man is seen riding a motorcycle in the street",
    "73": "a car is seen driving down the street with smoke coming out of it",
    "74": "a car is seen driving down the street with smoke coming out of it",
    "75": "a car is seen driving down the street with smoke coming out of it",
    "76": "a video of a car driving through the street",
    "77": "a video of a car being smashed into a tree",
    "78": "a video of a car being smashed into a tree",
    "79": "a video of a car being smashed into a tree",
    "80": "a video of a car being smashed into a tree",
    "81": "a video of a car being sprayed with water",
    "82": "a video of a car being smashed into a tree",
    "83": "a video of a car being smashed into a tree",
    "84": "a video of a car driving through a street",
    "85": "a video of a car driving through a street",
    "86": "a video of a car driving through the smoke",
    "87": "a video of a car driving through the streets",
    "88": "a video of a car driving through the streets",
    "89": "a video of a car driving through the street",
    "90": "a video of a car driving through the street",
    "91": "a video of a car driving through the street",
    "92": "a car is seen driving through the street",
    "93": "a video of a car driving through a street",
    "94": "a video of a car driving through the smoke",
    "95": "a car is seen driving through the street",
    "96": "a car is seen driving through the street",
    "97": "a car is seen driving through the street",
    "98": "a car is seen driving through the street",
    "99": "a car is seen driving through the street",
    "100": "a car is seen driving down the street",
    "101": "a video of a car driving down a street",
    "102": "a video of a car driving down a street",
    "103": "a video of a car driving down the street",
    "104": "a motorcycle is seen in the street with smoke coming out of it",
    "105": "a video of a car driving down the street",
    "106": "a video of a car driving down the street",
    "107": "a video of a car driving down the street",
    "108": "a video of a car driving down the street",
    "109": "a video of a car being pushed into the street",
    "110": "a car is seen driving down the street in a city",
    "111": "a car is seen driving down the street in a city",
    "112": "a video of a car driving down the street",
    "113": "a car is seen driving down the street in a city",
    "114": "a car is seen driving down the street in a city",
    "115": "a video of a car driving down the street",
    "116": "a video of a car driving down the street",
    "117": "a video of a car driving down the street",
    "118": "a video of a car driving down the street",
    "119": "a car is seen driving through the street",
    "120": "a car is seen driving down the street",
    "121": "a car is seen driving down the street",
    "122": "a video of a car driving down the street",
    "123": "a video of a car driving through the street",
    "124": "a video of a car driving down the street",
    "125": "a video of a car driving down the street",
    "126": "a video of a car driving down the street",
    "127": "a video of a car driving through the street",
    "128": "a car is seen driving down the street in the rain",
    "129": "a video of a car driving through a street",
    "130": "a video of a car driving through a street",
    "131": "a car is seen driving down the street in the rain",
    "132": "a car is seen driving down the street in the rain",
    "133": "a video of a car driving down a street",
    "134": "a car is seen driving down the street in the rain",
    "135": "a video of a car driving through a street",
    "136": "a video of a car driving through a street",
    "137": "a car is seen driving down a street in the rain",
    "138": "a car is seen driving in the rain",
    "139": "a car is seen driving through a flooded street",
    "140": "a video of a car driving through a street",
    "141": "a video of a car driving through a flooded street",
    "142": "a car is seen driving through a flooded street",
    "143": "a car is seen driving through a flooded street",
    "144": "a car is seen driving through a parking lot",
    "145": "a car is seen driving through a flooded street",
    "146": "a video of a car driving through a flooded street",
    "147": "a video of a car driving through a parking lot",
    "148": "a video of a car driving through a flooded street",
    "149": "a video of a car driving through a flooded street",
    "150": "a video of a car driving through a street",
    "151": "a video of a car driving through a street",
    "152": "a video of a car driving through a flooded street",
    "153": "a video of a car driving through a flooded street",
    "154": "a video of a car driving through a flooded street",
    "155": "a video of a car driving through a flooded street",
    "156": "a video of a car driving through a flooded street",
    "157": "a video of a car driving through a flooded street",
    "158": "a video of a car driving through a flooded street",
    "159": "a video of a car driving through a flooded street",
    "160": "a video of a car driving through a flooded street",
    "161": "a video of a car driving through a flooded street",
    "162": "a video of a car driving through a parking lot",
    "163": "a video of a car driving through a flooded street",
    "164": "a video of a car driving through a flooded street",
    "165": "a video of a car driving through a flooded street",
    "166": "a video of a car driving through a street",
    "167": "a video of a car driving through a flooded street",
    "168": "a video of a car driving through a parking lot",
    "169": "a video of a car driving in a parking lot",
    "170": "a video of a car driving in the rain",
    "171": "a video of a car driving through a flooded street",
    "172": "a video of a car driving in the rain",
    "173": "a video of a car driving in the rain",
    "174": "a video of a car driving in the rain",
    "175": "a video of a man walking in the street",
    "176": "a video of a man walking in the street",
    "177": "a video of a car driving through a parking lot",
    "178": "a video of a car driving in the rain",
    "179": "a video of a car in the middle of a flooded street",
    "180": "a video of a car in the middle of a flooded street",
    "181": "a video of a car in the middle of a flooded street",
    "182": "a video of a car in the middle of a flooded street",
    "183": "a video of a car in the middle of a flooded street",
    "184": "a video of a car in the middle of a flooded street",
    "185": "a video of a car in the middle of a flooded street",
    "186": "a video of a car in the middle of a flooded street",
    "187": "a video of a car in the middle of a street",
    "188": "a video of a car driving in the rain",
    "189": "a video of a man walking in the rain",
    "190": "a video of a car driving in the rain",
    "191": "a video of a car in the middle of a flooded street",
    "192": "a video of a car in the middle of a flooded street",
    "193": "a video of a car in the middle of a flooded street",
    "194": "a video of a car in the middle of a flooded street",
    "195": "a video of a car in the middle of a flooded street",
    "196": "a video of a car in the middle of a flooded street",
    "197": "a video of a car driving through a flooded street",
    "198": "a video of a car driving through a flooded street",
    "199": "a video of a car driving in the rain",
    "200": "a video of a car driving in the rain",
    "201": "a video of a car driving through a flooded street",
    "202": "a video of a car driving in the rain",
    "203": "a video of a car driving in the rain",
    "204": "a video of a car driving in the rain",
    "205": "a video of a car driving through a flooded street",
    "206": "a video of a car driving through a flooded street",
    "207": "a video of a car driving through a flooded street",
    "208": "a video of a car driving through a flooded street",
    "209": "a video of a car driving through a flooded street",
    "210": "a video of a car driving through a flooded street",
    "211": "a video of a car driving through a flooded street",
    "212": "a video of a car driving through a flooded street",
    "213": "a video of a car driving in the rain",
    "214": "a video of a car driving in the rain",
    "215": "a video of a car driving down the street",
    "216": "a video of a car driving down the street",
    "217": "a video of a car driving down the road",
    "218": "a video of a truck driving down the road",
    "219": "a truck is driving down the road with a camera",
    "220": "a video of a truck driving down the road",
    "221": "a video of a truck driving down the road",
    "222": "a view of a truck driving down the road",
    "223": "a car driving down the road with a truck in front of it",
    "224": "a car driving down the road with a truck behind it",
    "225": "a video of a truck driving down the road",
    "226": "a video of a truck driving down the road",
    "227": "a view of a truck driving down the road",
    "228": "a video of a truck driving down the road",
    "229": "a truck driving down the road with a camera in the front",
    "230": "a truck driving down the road with a camera in the front",
    "231": "a car driving down the road with a truck behind it",
    "232": "a truck driving down the road with a camera in the front",
    "233": "a truck driving down the road with a camera in the front",
    "234": "a truck driving down the road with a camera",
    "235": "a truck driving down the road with a camera",
    "236": "a truck driving down the road with a camera in the front",
    "237": "a video of a truck driving down the road",
    "238": "a truck driving down the road with a camera view",
    "239": "a truck driving down the road with a camera view",
    "240": "a truck driving down the road with a camera view",
    "241": "a view of a truck driving down the road",
    "242": "a view of a truck driving down the road",
    "243": "a view of a truck driving down the road",
    "244": "a view of a truck driving down the road",
    "245": "a view of a truck driving down the road",
    "246": "a view of a truck driving down the road",
    "247": "a view of a truck driving down the road",
    "248": "a view of a truck driving down the road",
    "249": "a view of a truck driving down the road",
    "250": "a truck driving down the road with a camera view",
    "251": "a view of a truck driving down the road",
    "252": "a view of a truck driving down the road",
    "253": "a view of a truck driving down the road",
    "254": "a view of a truck driving down the road",
    "255": "a view of a truck driving down the road",
    "256": "a view of a truck driving down the road",
    "257": "a view of a truck driving down the road",
    "258": "a view of a truck driving down the road",
    "259": "a view of a truck driving down the road",
    "260": "a view of a truck driving down the road",
    "261": "a view of a truck driving down the road",
    "262": "a view of a truck driving down the road",
    "263": "a view of a truck driving down the road",
    "264": "a car driving down the road with a truck behind it",
    "265": "a car driving down the road with a truck behind it",
    "266": "a view of a truck driving down the road",
    "267": "a view of a truck driving down the road",
    "268": "a view of a car driving down a road",
    "269": "a view of a truck driving down the road",
    "270": "a car driving down the road with a truck behind it",
    "271": "a car driving down the road with a truck behind it",
    "272": "a car driving down the road with a truck behind it",
    "273": "a car driving down the road with a truck behind it",
    "274": "a car driving down a road with trees in the background",
    "275": "a car driving down a road with trees in the background",
    "276": "a car driving down the road with a truck behind it",
    "277": "a truck driving down the road with a car behind it",
    "278": "a car driving down a road with a truck behind it",
    "279": "a car driving down a road with trees in the background",
    "280": "a truck driving down the road with a car behind it",
    "281": "a truck driving down the road with a car behind it",
    "282": "a car driving down the road with a truck behind it",
    "283": "a car driving down a road with trees in the background",
    "284": "a car driving down a road with a truck behind it",
    "285": "a car driving down the road with a truck behind it",
    "286": "a truck driving down the road with a camera view",
    "287": "a truck driving down the road with a camera view",
    "288": "a truck driving down the road with trees in the background",
    "289": "a truck driving down the road with a camera view",
    "290": "a truck driving down the road with a camera view",
    "291": "a truck driving down the road with a camera view",
    "292": "a truck driving down the road with a camera view",
    "293": "a truck driving down the road with a camera view",
    "294": "a truck driving down the road with a camera view",
    "295": "a view of a truck driving down the road",
    "296": "a truck driving down the road with a camera view",
    "297": "a view of a truck driving down the road",
    "298": "a truck driving down the road with a camera view",
    "299": "a truck driving down the road with a camera view",
    "300": "a truck driving down the road with a camera view",
    "301": "a truck driving down the road with a camera view",
    "302": "a truck driving down the road with a camera",
    "303": "a truck driving down a road with a camera view",
    "304": "a truck driving down a road with a camera view",
    "305": "a truck driving down the road with a camera view",
    "306": "a view of a truck driving down a road",
    "307": "a truck driving down a road with a camera view",
    "308": "a view of a truck driving down a road",
    "309": "a view of a truck driving down a road",
    "310": "a truck is driving down the road with a camera view",
    "311": "a truck is driving down the road with a camera",
    "312": "a truck is driving down the road with a camera",
    "313": "a truck is driving down the road with a camera",
    "314": "a truck driving down a road with trees in the background",
    "315": "a view of a truck driving down a road",
    "316": "a truck driving down a road with trees in the background",
    "317": "a truck is driving down the road with a camera",
    "318": "a truck is driving down the road with a camera",
    "319": "a truck driving down a road with a car behind it",
    "320": "a view of a truck driving down a road",
    "321": "a truck is driving down the road with a camera",
    "322": "a truck driving down a road with a car behind it",
    "323": "a truck is driving down a road with trees in the background",
    "324": "a truck driving down a road with a view of the trees",
    "325": "a view of a truck driving down a road",
    "326": "a view of a truck driving down a road",
    "327": "a view of a truck driving down a road",
    "328": "a view of a truck driving down a road",
    "329": "a view of a truck driving down a road",
    "330": "a view of a truck driving down a road",
    "331": "a view of a truck driving down a road",
    "332": "a view of a truck driving down a road",
    "333": "a view of a truck driving down a road",
    "334": "a view of a truck driving down a road",
    "335": "a view of a truck driving down the road",
    "336": "a truck is driving down the road with a camera",
    "337": "a truck is driving down the road with a camera",
    "338": "a truck is driving down the road with a camera",
    "339": "a truck is driving down the road with a camera",
    "340": "a truck is driving down the road with a camera",
    "341": "a truck is driving down the road with a camera",
    "342": "a truck is driving down the road with a camera",
    "343": "a truck is driving down the road with a camera",
    "344": "a truck is driving down the road with a camera",
    "345": "a truck is driving down the road with a camera",
    "346": "a truck is driving down the road with a camera",
    "347": "a truck is driving down the road with a camera",
    "348": "a truck is driving down the road with a camera",
    "349": "a truck is driving down the road with a camera",
    "350": "a truck is driving down the road with a camera",
    "351": "a truck is driving down the road with a camera",
    "352": "a truck is on the side of the road",
    "353": "a truck is driving down the road with a camera",
    "354": "a truck is driving down the road with a camera",
    "355": "a truck is driving down the road with a camera",
    "356": "a truck is driving down the road with a camera",
    "357": "a truck is driving down the road with a camera",
    "358": "a truck is driving down the road with a camera",
    "359": "a truck is driving down the road with a camera",
    "360": "a truck is driving down the road with a camera",
    "361": "a truck is driving down the road with a camera",
    "362": "a truck is driving down the road with a camera",
    "363": "a truck is driving down the road with a camera",
    "364": "a truck is driving down the road with a camera",
    "365": "a truck is driving down the road with a camera",
    "366": "a truck is driving down the road with a camera",
    "367": "a truck is driving down the road with a camera",
    "368": "a truck is driving down the road with a camera",
    "369": "a truck is driving down the road with a camera",
    "370": "a truck is driving down the road with a camera",
    "371": "a truck driving down the road with a camera",
    "372": "a truck driving down the road with a camera",
    "373": "a truck driving down the road with a camera",
    "374": "a truck driving down a road with trees in the background",
    "375": "a truck driving down the road with trees in the background",
    "376": "a truck driving down the road with trees in the background",
    "377": "a truck driving down a road with trees in the background",
    "378": "a truck driving down a road with trees in the background",
    "379": "a truck driving down a road with trees in the background",
    "380": "a truck driving down a road with trees in the background",
    "381": "a truck driving down a road with trees in the background",
    "382": "a truck driving down a road with trees in the background",
    "383": "a truck driving down a road with trees in the background",
    "384": "a truck driving down a road with trees in the background",
    "385": "a truck is driving down the road with a camera",
    "386": "a truck is driving down the road with a car behind it",
    "387": "a truck is driving down a road with trees in the background",
    "388": "a truck is driving down a road with trees in the background",
    "389": "a truck is driving down a road with trees in the background",
    "390": "a truck is driving down a road with trees in the background",
    "391": "a car is driving down a road with trees on the side",
    "392": "a truck is driving down a road with trees in the background",
    "393": "a truck is driving down a road with trees in the background",
    "394": "a truck is driving down a road with trees in the background",
    "395": "a truck is driving down a road with trees in the background",
    "396": "a truck is driving down a road with trees in the background",
    "397": "a truck is driving down a road with trees in the background",
    "398": "a truck is driving down a road with trees in the background",
    "399": "a truck is driving down a road with trees in the background",
    "400": "a truck is driving down a road with trees in the background",
    "401": "a truck is driving down a road with trees in the background",
    "402": "a car is driving down a road with a truck on it",
    "403": "a truck is driving down a road with trees in the background",
    "404": "a car is driving down a road with trees on the side",
    "405": "a car is driving down a road with trees on the side",
    "406": "a truck is driving down a road with trees in the background",
    "407": "a truck is flipped over on a road",
    "408": "a car is driving down a road with a truck on it",
    "409": "a car is driving down a road with trees on the side",
    "410": "a car driving down a road with trees on the side",
    "411": "a car driving down a road with trees on the side",
    "412": "a car is driving down a road with trees on the side",
    "413": "a car is driving down a road with trees on the side",
    "414": "a car is driving down a road with trees on the side",
    "415": "a car is driving down a road with trees on the side",
    "416": "a car driving down a road with trees on the side",
    "417": "a car driving down a road with trees on the side",
    "418": "a car driving down a road with trees on the side",
    "419": "a car driving down a road with trees on the side",
    "420": "a car driving down a road with trees on the side",
    "421": "a car driving down a road with trees on the side",
    "422": "a car driving down a road with trees on the side",
    "423": "a view of the road from the inside of a car",
    "424": "a car driving down a road with trees on the side",
    "425": "a view of the road from the driver's seat",
    "426": "a car driving down a road with trees on the side",
    "427": "a car driving down a road with trees on the side",
    "428": "a car driving down a road with trees on both sides",
    "429": "a car driving down a road with trees on the side",
    "430": "a car driving down a road with trees on both sides",
    "431": "a car driving down a road with trees on the side",
    "432": "a car driving down a road with trees on the side",
    "433": "a car driving down a road with trees on the side",
    "434": "a car driving down a road with trees on the side",
    "435": "a car driving down a road with trees on the side",
    "436": "a car driving down a road with trees on the side",
    "437": "a car driving down a road with trees in the background",
    "438": "a car is driving down a road with trees in the background",
    "439": "a car is driving down a road with trees in the background",
    "440": "a car is driving down a road with trees on the side",
    "441": "a car is driving down a road with trees in the background",
    "442": "a car is driving down a road with trees in the background",
    "443": "a car is driving down a road with trees on it",
    "444": "a car is driving down a road with trees on the side",
    "445": "a car is driving down a road with trees on the side",
    "446": "a car is driving down a road with trees in the background",
    "447": "a car is driving down a road with trees in the background",
    "448": "a car is driving down a road with trees in the background",
    "449": "a car is driving down a road with trees in the background",
    "450": "a car is driving down a road with trees on the side",
    "451": "a car is driving down a road with trees on the side",
    "452": "a car is driving down a road with trees in the background",
    "453": "a car is driving down a road with trees in the background",
    "454": "a car is driving down a road with trees in the background",
    "455": "a car is driving down a road with trees on the side",
    "456": "a car is driving down a road with trees on the side",
    "457": "a car is driving down a road with trees in the background",
    "458": "a car is driving down a road with trees on the side",
    "459": "a car is driving down a road with trees in the background",
    "460": "a car is driving down a road with a large truck on it",
    "461": "a car is driving down a road with trees on the side",
    "462": "a car is driving down a road with trees on the side",
    "463": "a car is driving down a road with a large truck",
    "464": "a car is driving down a road with a lot of dirt",
    "465": "a car is driving down a road with trees in the background",
    "466": "a car is driving down a road with trees in the background",
    "467": "a car is driving down a road with a large truck",
    "468": "a car is driving down a road with trees in the background",
    "469": "a car is driving down a road with a large truck in front of it",
    "470": "a car is driving down a road with a large truck in front of it",
    "471": "a car is driving down a road with a lot of dirt",
    "472": "a car is driving down a road with a lot of trees",
    "473": "a car is driving down a road with a large truck in front of it",
    "474": "a car is driving down a road with trees in the background",
    "475": "a car is driving down a road with a truck in front of it",
    "476": "a car is driving down a road with a large truck",
    "477": "a car is driving down a road with a large truck",
    "478": "a car is driving down a road with trees in the background",
    "479": "a car is driving down a road with trees in the background",
    "480": "a car is driving down a road with trees in the background",
    "481": "a car is driving down a road with trees in the background",
    "482": "a car is driving down a road with trees in the background",
    "483": "a car is driving down a road with trees in the background",
    "484": "a car is driving down a road with trees in the background",
    "485": "a car is driving down a road with trees in the background",
    "486": "a truck is driving down a road with trees in the background",
    "487": "a car is driving down a road with a truck in front of it",
    "488": "a truck is driving down a road with trees in the background",
    "489": "a truck is driving down a road with trees in the background",
    "490": "a truck is driving down a road with trees in the background",
    "491": "a truck is driving down a road with trees in the background",
    "492": "a truck is driving down a road with trees in the background",
    "493": "a truck is driving down a road with trees in the background",
    "494": "a truck is driving down a road with trees in the background",
    "495": "a truck is driving down a road with trees in the background",
    "496": "a truck is driving down a road with a lot of dust",
    "497": "a truck is driving down a road with trees in the background",
    "498": "a truck is driving down a road with trees in the background",
    "499": "a truck is driving down a road with trees in the background",
    "500": "a truck is driving down a road with trees in the background",
    "501": "a truck is driving down a road with trees in the background",
    "502": "a truck is driving down a road with trees in the background",
    "503": "a truck is driving down a road with trees in the background",
    "504": "a truck is driving down a road with trees in the background",
    "505": "a truck is driving down a road with trees in the background"
}