{
    "0": "a group of men are sitting at a table in a dark room",
    "1": "a group of men are sitting at a table in a dark room",
    "2": "a group of men are sitting at a table in a dark room",
    "3": "a group of people sitting at a table with computers",
    "4": "a group of men are sitting at a table in a dark room",
    "5": "a group of men are sitting at a table in a dark room",
    "6": "a group of men are sitting at a table in a dark room",
    "7": "a group of men are sitting at a table in a dark room",
    "8": "a group of men are sitting at a table with computers",
    "9": "a group of men are sitting at a table in a dark room",
    "10": "a group of people sitting at a table with computers",
    "11": "a group of men are sitting at a table with computers",
    "12": "a group of men are sitting at a table in a room",
    "13": "a group of men are sitting at a table with computers",
    "14": "a group of men sitting at a table with computers",
    "15": "a group of men are sitting at a table with computers",
    "16": "a group of men sitting at a table with computers",
    "17": "a group of men sitting at a table with computers",
    "18": "a group of men sitting at a table with computers",
    "19": "a man is talking to a television in the dark",
    "20": "a man in a green shirt is looking at something",
    "21": "a man in a t-shirt is looking at something",
    "22": "a man is looking at a television in the dark",
    "23": "a man is looking at a phone in the dark",
    "24": "a man is looking at a phone in the dark",
    "25": "a man is looking at a phone in the dark",
    "26": "a man is looking at a television in the dark",
    "27": "a man is looking at a tv screen in the dark",
    "28": "a man is looking at his phone in the dark",
    "29": "a man is holding his hand up in the dark",
    "30": "a man is holding his phone in his hand",
    "31": "a man is looking at something in the dark",
    "32": "a man is holding his hand up in the dark",
    "33": "a man is looking at something in the dark",
    "34": "a man is holding a baseball bat in his hand",
    "35": "a man is holding his hand up in the dark",
    "36": "a man is holding his hand up in the dark",
    "37": "a man is looking at his phone in the dark",
    "38": "a man is holding his phone in his hand",
    "39": "a man is looking at something in the dark",
    "40": "a man is holding a phone in his hand",
    "41": "a man is looking at his phone in the dark",
    "42": "a man is looking at his phone in the dark",
    "43": "a man is looking at his phone in the dark",
    "44": "a man is looking at his phone in the dark",
    "45": "a man with blue eyes is looking at something in the dark",
    "46": "a man in a dark room with his hand on his phone",
    "47": "a man with a blue eye is looking at something",
    "48": "a man is looking at a phone in the dark",
    "49": "a man with blue eyes is looking at something in the dark",
    "50": "a man with blue eyes is looking at something",
    "51": "a man with blue eyes is looking at something in the dark",
    "52": "a man in a dark room with his head down",
    "53": "a man with blue eyes is looking at something in the dark",
    "54": "a man in a dark room with his hand on his phone",
    "55": "a man with blue eyes is looking at something in the dark",
    "56": "a man in a dark room looking at something",
    "57": "a man in a dark room looking at something",
    "58": "a man in a dark room with a tv on",
    "59": "a man is looking at something in the dark",
    "60": "a man is looking at something in the dark",
    "61": "a man is looking at something in the dark",
    "62": "a man is looking at something in the dark",
    "63": "a man is looking at something in the dark",
    "64": "a man is looking at something in the dark",
    "65": "a man is looking at something in the dark",
    "66": "a man is looking at something in the dark",
    "67": "a man is looking at something in the dark",
    "68": "a man is looking at something in the dark",
    "69": "a man in a green shirt is looking at the camera",
    "70": "a man is looking at the camera in the dark",
    "71": "a man is looking at something in the dark",
    "72": "a man in a dark room looking at a tv",
    "73": "a man is looking at the camera in the dark",
    "74": "a man in a green shirt is looking at something in the dark",
    "75": "a man is looking at his phone in the dark",
    "76": "a man is looking at his phone in the dark",
    "77": "a man in a dark room looking at something",
    "78": "a man in a dark room with his hand on his shoulder",
    "79": "a man in a dark room looking at something",
    "80": "a man in a dark room looking at something",
    "81": "a man in a green shirt is staring at a tv",
    "82": "a man in a green shirt is looking at something",
    "83": "a man in a green shirt is looking at something",
    "84": "a man in a dark room with his eyes closed",
    "85": "a man with blue eyes is looking at something in the dark",
    "86": "a man in a dark room with his hand on his shoulder",
    "87": "a man in a dark room with his hand on his phone",
    "88": "a man in a dark room with his hand on his shoulder",
    "89": "a man in a dark room with his hand on his shoulder",
    "90": "a picture of a man with a knife in his hand",
    "91": "a picture of a man with a knife in his hand",
    "92": "a picture of a man with a gun in his hand",
    "93": "a picture of a man with a gun in his hand",
    "94": "a picture of a person using a drill",
    "95": "a picture of a person cutting a tree in a dark room",
    "96": "a picture of a person cutting a tree in a dark room",
    "97": "a person is using a tool to cut a pipe",
    "98": "a picture of a person with a knife in his hand",
    "99": "a picture of a person with a knife in his hand",
    "100": "a picture of a person holding a knife",
    "101": "a picture of a person with a knife in his hand",
    "102": "a picture of a person with a knife in his hand",
    "103": "a person is holding a broom in a dark room",
    "104": "a picture of a person with a knife in his hand",
    "105": "a picture of a person with a knife in his hand",
    "106": "a picture of a person with a toothbrush in his hand",
    "107": "a picture of a person with a toothbrush in his hand",
    "108": "a person is laying in the water with a toothbrush",
    "109": "a picture of a person in a dark room",
    "110": "a picture of a person with a knife in his hand",
    "111": "a picture of a person with a knife in his hand",
    "112": "a picture of a person with a knife in his hand",
    "113": "a picture of a man with a shovel in the snow",
    "114": "a person is sitting in a dark room with a flashlight",
    "115": "a picture of a person in a dark room",
    "116": "a person is putting a shovel into a hole",
    "117": "a picture of a man with a knife in his hand",
    "118": "a picture of a man with a knife in his hand",
    "119": "a picture of a person with a knife in his hand",
    "120": "a picture of a person with a toothbrush in his hand",
    "121": "a picture of a person in a dark room",
    "122": "a picture of a person with a toothbrush in his hand",
    "123": "a picture of a person with a knife in his hand",
    "124": "a picture of a person with a knife in his hand",
    "125": "a picture of a person with a toothbrush in his hand",
    "126": "a picture of a person with a toothbrush in his hand",
    "127": "a picture of a toothbrush in the water",
    "128": "a picture of a man with a knife in his hand",
    "129": "a person is laying on a bed with a knife",
    "130": "a person is laying on a bed with a knife",
    "131": "a person is laying in the water with a knife",
    "132": "a person is sitting on a chair in the dark",
    "133": "a person is laying on a bed in the dark",
    "134": "a picture of a person in the water",
    "135": "a picture of a person in the water",
    "136": "a picture of a person in the water",
    "137": "a picture of a tv set in the water",
    "138": "a picture of a tv set in the water",
    "139": "a picture of a person in a dark room",
    "140": "a picture of a person with a knife in his hand",
    "141": "a picture of a person with a knife in his hand",
    "142": "a picture of a tv set in the water",
    "143": "a picture of a person with a knife in his hand",
    "144": "a picture of a person with a knife in his hand",
    "145": "a picture of a person in a dark room",
    "146": "a man with a green shirt is looking at a tv",
    "147": "a man in a green shirt is looking at a tv",
    "148": "a man in a green shirt is looking at a tv",
    "149": "a man is holding his hand up in the dark",
    "150": "a man with a green shirt is looking at something",
    "151": "a man with a green shirt is looking at something",
    "152": "a man with a green shirt is looking at a tv",
    "153": "a man with a green shirt is looking at a tv",
    "154": "a man with a green shirt is looking at something",
    "155": "a man with a green shirt is looking at something",
    "156": "a man is holding his hand up in the dark",
    "157": "a man is holding his hand up in the dark",
    "158": "a man is holding his hand up in the dark",
    "159": "a man is holding his hand up in the dark",
    "160": "a man is holding his hand up in the dark",
    "161": "a man is looking at a tv screen in the dark",
    "162": "a man is looking at a tv in the dark",
    "163": "a man in a green shirt is looking at something",
    "164": "a man in a green shirt is looking at something",
    "165": "a man in a green shirt is looking at something",
    "166": "a man in a green shirt is looking at the camera",
    "167": "a man in a green shirt is looking at something",
    "168": "a man in a green shirt is looking at something",
    "169": "a man in a green shirt is looking at the camera",
    "170": "a man in a green shirt is looking at something",
    "171": "a man in a green shirt is looking at the camera",
    "172": "a man in a green shirt is looking at something",
    "173": "a man with his eyes closed is looking at a tv",
    "174": "a man with his eyes closed is looking at a tv",
    "175": "a man is looking at his phone in the dark",
    "176": "a man in a green shirt is looking at the camera",
    "177": "a man in a green shirt is looking at the camera",
    "178": "a man in a green shirt is looking at something",
    "179": "a man in a green shirt is looking at something",
    "180": "a man with a green shirt is looking at something",
    "181": "a man with a green shirt is looking at something",
    "182": "a man in a green shirt is looking at something",
    "183": "a man with a green shirt is looking at something",
    "184": "a man with a green shirt is looking at something",
    "185": "a man with a green shirt is looking at something",
    "186": "a man with a green shirt is looking at something",
    "187": "a person looking out a window at a dirt area",
    "188": "a view of a dirt field with a few tents",
    "189": "a person is looking out over a dirt field",
    "190": "a person is looking out over a dirt field",
    "191": "a person is looking out over a dirt field",
    "192": "a person is looking down at a dirt field",
    "193": "a person is looking down at a dirt field",
    "194": "a person is looking down at a dirt field",
    "195": "a person is looking down at a dirt field",
    "196": "a person is shooting a gun from a window",
    "197": "a person is looking down at a dirt field",
    "198": "a person is looking out over a city from a window",
    "199": "a person is looking out a window at a dirt field",
    "200": "a person is looking out a window at a dirt field",
    "201": "a person is looking out a window at a dirt field",
    "202": "a person is looking out a window at a dirt field",
    "203": "a person is looking out a window at a dirty area",
    "204": "a person is looking out a window at a dirt field",
    "205": "a person is looking down at a dirt field",
    "206": "a person is looking down at a dirt field",
    "207": "a man is shooting a gun from a window",
    "208": "a man is looking down at a building from a window",
    "209": "a man is looking down at a dirt field",
    "210": "a man is shooting a gun from a window",
    "211": "a man is looking down at a dirt field",
    "212": "a person is looking down at a dirt field",
    "213": "a person is looking down at a dirt field",
    "214": "a person is looking down at a dirt field",
    "215": "a group of soldiers are laying on the ground near a building",
    "216": "a group of soldiers are laying on the ground near a building",
    "217": "a group of soldiers are laying on the ground near a building",
    "218": "a group of soldiers are laying on the ground near a building",
    "219": "a group of soldiers are standing near a car",
    "220": "a group of soldiers are laying on the ground near a building",
    "221": "a group of soldiers are laying on the ground near a building",
    "222": "a group of soldiers are laying on the ground near a building",
    "223": "a group of soldiers are laying on the ground near a building",
    "224": "a group of soldiers are surrounded by a building",
    "225": "a group of soldiers are laying on the ground near a building",
    "226": "a group of soldiers are surrounded by a building",
    "227": "a group of soldiers are battling in the dirt",
    "228": "a group of soldiers are battling in the dirt",
    "229": "a group of soldiers are battling in the dirt",
    "230": "a group of soldiers are battling in the dirt",
    "231": "a group of soldiers are battling in the dirt",
    "232": "a group of soldiers are fighting in the dirt",
    "233": "a group of soldiers are fighting in the dirt",
    "234": "a group of soldiers are fighting near a building",
    "235": "a group of soldiers are shooting at a car",
    "236": "a group of soldiers are fighting in the dirt",
    "237": "a group of soldiers are fighting in the dirt",
    "238": "a group of soldiers are fighting in the dirt",
    "239": "a group of soldiers are fighting in the dirt",
    "240": "a group of people are running around a building",
    "241": "a group of men are running around a building",
    "242": "a group of soldiers are laying on the ground near a building",
    "243": "a person in a hoodie is walking down a street",
    "244": "a man in a helmet is looking at a wall",
    "245": "a man in a helmet is looking at a wall",
    "246": "a man is holding a gun in a dirty area",
    "247": "a man in a helmet is shooting a gun",
    "248": "a man in a hooded shirt is shooting a gun",
    "249": "a man in a helmet is shooting a gun",
    "250": "a man in a mask is holding a gun",
    "251": "a man in a hoodie is shooting a gun",
    "252": "a man in a mask is looking at a wall",
    "253": "a man is sitting on a dirt floor near a wall",
    "254": "a man in a helmet is shooting a gun at a wall",
    "255": "a man in a helmet is looking at a wall",
    "256": "a man in a helmet is standing in a dark area",
    "257": "a man in a helmet is shooting a gun at a wall",
    "258": "a man in a helmet is standing next to a wall",
    "259": "a man is shooting a gun at a wall",
    "260": "a man in a hoodie is shooting at a wall",
    "261": "a man in a hoodie is shooting a gun",
    "262": "a man is shooting a gun at a wall",
    "263": "a man in a hood shooting a gun at a wall",
    "264": "a man in a hoodie is shooting at a wall",
    "265": "a man in a hoodie is standing in a dirt area",
    "266": "a man in a hoodie is shooting a gun",
    "267": "a man in a helmet is standing next to a wall",
    "268": "a man in a mask is standing next to a wall",
    "269": "a man in a mask is spraying smoke at a wall",
    "270": "a man in a hoodie is standing next to a wall",
    "271": "a man in a hooded jacket is shooting at a wall",
    "272": "a man in a black hoodie shooting a gun",
    "273": "a man is shooting at a wall with smoke coming out of his gun",
    "274": "a man in a hooded jacket is shooting a gun",
    "275": "a man in a helmet is shooting at a wall",
    "276": "a man in a mask is shooting at a wall",
    "277": "a man is looking at a camera through a window",
    "278": "a man with a gun in his face",
    "279": "a man with a gun in his face",
    "280": "a man is holding a gun in his hand",
    "281": "a man with a gun in his hand",
    "282": "a man holding a gun in his hand",
    "283": "a man holding a gun in his hand",
    "284": "a man holding a gun in his hand",
    "285": "a man is holding a gun in his face",
    "286": "a man holding a gun in his hand",
    "287": "a man with a gun is looking at the camera",
    "288": "a man with a gun in his hand looking through a window",
    "289": "a man is holding a gun in his hand",
    "290": "a man is holding a gun in his hand",
    "291": "a man holding a gun in his hand",
    "292": "a man is holding a gun in his hand",
    "293": "a man is holding a gun in his hand",
    "294": "a man with a gun in his hand looking at a mirror",
    "295": "a man is looking at a gun in a car",
    "296": "a man is holding a gun in his hand",
    "297": "a man is holding a gun in his hand",
    "298": "a man is holding a gun in his hand",
    "299": "a man is holding a gun in his hand",
    "300": "a man is looking at a camera through a window",
    "301": "a man is holding a gun in his hand",
    "302": "a close up of a rusty bike with a handlebar",
    "303": "a man holding a gun in a mirror",
    "304": "a man is holding a gun in his hand",
    "305": "a man is holding a gun in his hand",
    "306": "a man is holding a gun in his hand",
    "307": "a man is holding a gun in his hand",
    "308": "a man is looking at a gun through a window",
    "309": "a man is holding a gun in his hand",
    "310": "a man is holding a gun in his hand",
    "311": "a man holding a gun in his hand",
    "312": "a man is holding a gun in his hand",
    "313": "a man is holding a gun in his hand",
    "314": "a man with a rifle looking through a window",
    "315": "a man with a gun looking at a wall",
    "316": "a man is looking at a gun through a window",
    "317": "a man is looking at a gun in a mirror",
    "318": "a man is holding a gun in his hand",
    "319": "a man is holding a gun in his hand",
    "320": "a group of soldiers are shooting at a car",
    "321": "a group of soldiers are shooting at a car",
    "322": "a group of soldiers are shooting at a car",
    "323": "a group of soldiers are shooting at a car",
    "324": "a group of soldiers are shooting at a car",
    "325": "a group of soldiers are shooting at a car",
    "326": "a group of soldiers are shooting at a car",
    "327": "a group of soldiers are shooting at a car",
    "328": "a group of soldiers are shooting at a car",
    "329": "a group of soldiers are shooting at a car",
    "330": "a group of soldiers are shooting at a car",
    "331": "a group of soldiers are shooting at a car",
    "332": "a group of soldiers are shooting at a car",
    "333": "a group of soldiers are shooting at a car",
    "334": "a group of soldiers are shooting at a car",
    "335": "a group of soldiers with guns are running towards a car",
    "336": "a group of soldiers with guns are running towards a car",
    "337": "a group of soldiers are shooting at a car",
    "338": "a group of soldiers are shooting at a car",
    "339": "a group of soldiers with guns in a movie",
    "340": "a group of soldiers are shooting at a car",
    "341": "a group of soldiers with guns in a movie",
    "342": "a group of soldiers with guns are chasing a car",
    "343": "a group of soldiers are shooting at a car",
    "344": "a group of soldiers with guns are chasing a car",
    "345": "a group of soldiers with guns are chasing a car",
    "346": "a group of soldiers with guns are chasing a car",
    "347": "a group of soldiers with guns are chasing a car",
    "348": "a group of soldiers with guns are chasing a car",
    "349": "a group of soldiers with guns are chasing a car",
    "350": "a group of soldiers are in a muddy area",
    "351": "a group of soldiers are standing in a room",
    "352": "a soldier is talking on a cell phone",
    "353": "a soldier is talking on a radio while another soldier is standing",
    "354": "a soldier in a military uniform talking on a cell phone",
    "355": "a soldier is talking on a cell phone",
    "356": "a soldier is talking on a cell phone while he is in a military uniform",
    "357": "a soldier is talking to another soldier in a movie",
    "358": "a man in a military uniform is smiling",
    "359": "a man in a military uniform is looking at something",
    "360": "a man in a military uniform is smiling",
    "361": "a man in a military uniform is looking at something",
    "362": "a man in a military uniform is looking at something",
    "363": "a man in a military uniform is looking at something",
    "364": "a man in a helmet and helmet is looking at something",
    "365": "a man in a military uniform is looking at something",
    "366": "a man in a military uniform is looking at something",
    "367": "a man in a military uniform is looking at something",
    "368": "a man in a military uniform is looking at something",
    "369": "a man in a military uniform is looking at something",
    "370": "a man in a military uniform is looking at something",
    "371": "a man in a helmet is looking at something",
    "372": "a soldier in a helmet is looking at something",
    "373": "a soldier in a camouflage uniform is shouting",
    "374": "a man in a military uniform is walking down the street",
    "375": "a man in a military uniform is looking at something",
    "376": "a man in a military uniform is looking at something",
    "377": "a soldier in a helmet and helmet is talking",
    "378": "a soldier in a helmet and helmet is looking at something",
    "379": "a soldier in a helmet and helmet is looking at something",
    "380": "a man in a military uniform is looking at something",
    "381": "a man in a military uniform is looking at something",
    "382": "a man in a military uniform is holding a gun",
    "383": "a man in a helmet is looking at something",
    "384": "a man in a helmet is looking at something",
    "385": "a man in a helmet is looking at a car",
    "386": "a man in a helmet is looking at a car",
    "387": "a soldier in a helmet is walking through a cluttered area",
    "388": "a soldier in a helmet is standing next to a car",
    "389": "a soldier in a helmet is looking at a car",
    "390": "a soldier in a helmet is looking at a car",
    "391": "a soldier in a helmet is looking at a car",
    "392": "a soldier in a helmet is looking at a car",
    "393": "a soldier in a helmet is looking at a car",
    "394": "a soldier in a helmet is looking at a car",
    "395": "a soldier in a helmet is looking at a car",
    "396": "a soldier in a helmet is looking at a car",
    "397": "a soldier in a helmet is looking at a car",
    "398": "a soldier in a helmet is looking at a car",
    "399": "a soldier in a helmet is driving a car",
    "400": "a man in a military uniform is driving a vehicle",
    "401": "a soldier in a helmet and helmet is standing in a vehicle",
    "402": "a soldier in a military uniform is driving a vehicle",
    "403": "a soldier in a helmet and helmet is driving a car",
    "404": "a soldier in a helmet is driving a car",
    "405": "a soldier in a helmet and helmet is driving a car",
    "406": "a soldier in a helmet is walking down the street",
    "407": "a soldier in a camouflage uniform is driving a car",
    "408": "a soldier in a helmet and a helmet",
    "409": "a soldier in a helmet is standing next to a car",
    "410": "a soldier in a helmet and helmet is standing next to a car",
    "411": "a soldier in a helmet and helmet is talking on a phone",
    "412": "a soldier in a helmet and helmet is driving a car",
    "413": "a man in a military uniform driving a vehicle",
    "414": "a man in a military uniform driving a car",
    "415": "a man in a military uniform driving a vehicle",
    "416": "a man in a military uniform driving a vehicle",
    "417": "a man in a military uniform driving a truck",
    "418": "a man in a military uniform driving a truck",
    "419": "a man in a military uniform driving a truck",
    "420": "a man in a military uniform driving a vehicle",
    "421": "a man in a military uniform driving a car",
    "422": "a man in a military uniform driving a vehicle",
    "423": "a man in a military uniform driving a vehicle",
    "424": "a man in a military uniform driving a vehicle",
    "425": "a man in a military uniform driving a vehicle",
    "426": "a man in a military uniform driving a vehicle",
    "427": "a man in a military uniform driving a truck",
    "428": "a man in a military uniform driving a truck",
    "429": "a man in a military uniform driving a vehicle",
    "430": "a man in a military uniform driving a truck",
    "431": "a man in a military uniform driving a truck",
    "432": "a man in a military uniform driving a truck",
    "433": "a man in a military uniform driving a truck",
    "434": "a man in a military uniform driving a vehicle",
    "435": "a man in a military uniform driving a vehicle",
    "436": "a man in a military uniform driving a vehicle",
    "437": "a man in a military uniform driving a vehicle",
    "438": "a man in a military uniform driving a vehicle",
    "439": "a man in a military uniform is driving a vehicle",
    "440": "a man in a military uniform driving a car",
    "441": "a man in a military uniform driving a vehicle",
    "442": "a man in a military uniform driving a vehicle",
    "443": "a man in a military uniform is driving a car",
    "444": "a man in a military uniform driving a vehicle",
    "445": "a man in a military uniform driving a car",
    "446": "a man in a military uniform driving a vehicle",
    "447": "a man in a military uniform driving a vehicle",
    "448": "a man in a military uniform is driving a vehicle",
    "449": "a man in a military uniform is driving a vehicle",
    "450": "a man in a military uniform is driving a truck",
    "451": "a man in a military uniform is driving a vehicle",
    "452": "a man in a military uniform driving a vehicle",
    "453": "a man in a military uniform driving a vehicle",
    "454": "a man in a military uniform is driving a vehicle",
    "455": "a man in a military uniform is driving a car",
    "456": "a man in a military uniform is driving a vehicle",
    "457": "a soldier in a military uniform is seen through a window",
    "458": "a man in a military uniform is seen in a rear view mirror",
    "459": "a man in a military uniform is driving a car",
    "460": "a man in a military uniform is driving a vehicle",
    "461": "a man in a military uniform is looking out of a car window",
    "462": "a soldier in a military uniform is looking out of a window",
    "463": "a soldier in a military uniform is looking out of a window",
    "464": "a soldier in a military uniform is looking out of a window",
    "465": "a soldier is seen in a mirror of a car",
    "466": "a man in a helmet is looking out of a window",
    "467": "a man is holding a gun in his hand",
    "468": "a close up of a bicycle with a handlebar attached",
    "469": "a man is looking through a window at a person",
    "470": "a man holding a gun in his hand",
    "471": "a man in a military uniform holding a gun",
    "472": "a man holding a gun in a car",
    "473": "a man is holding a gun in his hand",
    "474": "a man holding a gun in a vehicle",
    "475": "a man with a gun looking through a window",
    "476": "a man with a gun looking through a window",
    "477": "a man holding a gun in a vehicle",
    "478": "a man with a gun looking through a window",
    "479": "a man in a helmet is holding a gun",
    "480": "a man holding a gun in his hand",
    "481": "a man in a helmet looking out of a window",
    "482": "a man in a helmet is looking through a window",
    "483": "a man in a helmet is looking at a gun",
    "484": "a man in a helmet is looking at a gun",
    "485": "a man holding a gun in his hand",
    "486": "a man holding a gun in his hand",
    "487": "a man with a gun looking through a window",
    "488": "a man with a gun looking through a window",
    "489": "a man holding a gun while looking through a window",
    "490": "a man with a gun looking at something",
    "491": "a man with a gun looking at something",
    "492": "a group of tents and a truck in a dirt field",
    "493": "a group of tents and a truck in a dirt field",
    "494": "a group of tents and a truck in a dirt field",
    "495": "a group of people are standing around a dirt area",
    "496": "a group of tents in a dirt field",
    "497": "a group of people are sitting in a dirt field",
    "498": "a group of people are sitting in a dirt field",
    "499": "a group of people are sitting in a dirt field",
    "500": "a group of tents and a dirt field",
    "501": "a group of tents and a boat in a dirt field",
    "502": "a group of tents in a dirt field",
    "503": "a dirt field with a lot of tents and a truck",
    "504": "a dirt field with a lot of tents and a boat",
    "505": "a dirt field with a lot of dirt and a few huts",
    "506": "a dirt field with a lot of green domes",
    "507": "a dirt field with a lot of tents and a boat",
    "508": "a dirt field with a lot of dirt and a few buildings",
    "509": "a dirt field with a lot of tents and huts",
    "510": "a dirt field with a lot of dirt and a few tents",
    "511": "a dirt field with a lot of dirt and a few buildings",
    "512": "a dirt field with a lot of tents and huts",
    "513": "a dirt field with a lot of dirt and a few buildings",
    "514": "a dirt field with a few huts and a boat",
    "515": "a dirt field with a lot of trash and a boat",
    "516": "a dirt field with a few huts and a wall",
    "517": "a dirt field with a few huts and a wall",
    "518": "a dirt field with a few buildings and a wall",
    "519": "a dirt field with a lot of dirt and a few buildings",
    "520": "a dirt field with a lot of trash and dirt",
    "521": "a dirt field with a few buildings and a tree",
    "522": "a dirt field with a lot of trash and dirt",
    "523": "a dirt field with a car in it",
    "524": "a dirt field with a dirt wall and a dirt road",
    "525": "a dirt field with a dirt wall and a trash can",
    "526": "a dirt field with a lot of trash and dirt",
    "527": "a dirt field with a lot of dirt and trash",
    "528": "a dirt field with a lot of trash and dirt",
    "529": "a dirt field with a dirt wall and a dirt road",
    "530": "a dirt field with a dirt wall and a dirt road",
    "531": "a dirt road with a dirt wall and a dirt road",
    "532": "a dirt road with a dirt wall and a dirt road",
    "533": "a dirt road with a dirt wall and a dirt road",
    "534": "a dirt road with a dirt wall and a dirt road",
    "535": "a dirt field with a dirt wall and a dirt road",
    "536": "a dirt road with a dirt wall and a dirt road",
    "537": "a dirt field with a building and a tree",
    "538": "a dirt road with a dirt wall and a tank",
    "539": "a dirt road with a dirt road and a dirt wall",
    "540": "a dirt road with a dirt road and a dirt road",
    "541": "a dirt road with a dirt wall and a dirt road",
    "542": "a view of a dirt field with a fire engine",
    "543": "a view of a dirt field with a train in the distance",
    "544": "a view of a building with a fire going on",
    "545": "a view of a building with a dirt area",
    "546": "two soldiers are holding guns in front of a wall",
    "547": "two soldiers are holding guns in front of a wall",
    "548": "two soldiers are holding guns in front of a wall",
    "549": "two soldiers in uniforms with guns",
    "550": "two soldiers in uniform with a gun",
    "551": "two soldiers in uniforms with guns",
    "552": "two soldiers in uniform with a gun",
    "553": "two soldiers in uniforms with guns",
    "554": "two soldiers with guns in front of a wall",
    "555": "two soldiers in uniforms are holding guns",
    "556": "two men in military gear are aiming their guns",
    "557": "two soldiers in uniforms are looking at a wall",
    "558": "two soldiers are holding guns and looking at a wall",
    "559": "two soldiers are holding guns and one is holding a gun",
    "560": "two soldiers are holding guns and are looking at each other",
    "561": "two soldiers are holding guns and looking at each other",
    "562": "two soldiers are holding guns and looking at a wall",
    "563": "two soldiers are holding guns and looking at a wall",
    "564": "two soldiers are holding guns in front of a wall",
    "565": "two soldiers are holding guns and are shooting at each other",
    "566": "two soldiers are holding a machine gun",
    "567": "a soldier is holding a gun and looking at a wall",
    "568": "a group of soldiers are aiming their guns at a wall",
    "569": "a group of soldiers are aiming their guns at a wall",
    "570": "a group of soldiers are aiming their guns at a wall",
    "571": "a group of soldiers are aiming their guns at a wall",
    "572": "a group of soldiers are aiming their guns at a wall",
    "573": "a group of soldiers are leaning against a wall",
    "574": "a group of soldiers are posing for a picture",
    "575": "a group of soldiers are aiming their guns at a wall",
    "576": "a group of soldiers are posing in front of a wall",
    "577": "a group of soldiers are posing in front of a wall",
    "578": "a group of soldiers are posing for a picture",
    "579": "a group of soldiers are posing in front of a wall",
    "580": "a group of soldiers are pointing their guns at a wall",
    "581": "a man is standing on a hill with a gun",
    "582": "a man is standing on a hill with a phone",
    "583": "a man is throwing a frisbee in the dirt",
    "584": "a man is throwing a frisbee in the air",
    "585": "a man is running away from a building with a gun",
    "586": "a man is standing on a hill with a gun",
    "587": "a man is walking on a hill with a phone",
    "588": "a man is throwing a frisbee into a pile of dirt",
    "589": "a man is running down a hill with a lot of debris",
    "590": "a man is running through a pile of dirt",
    "591": "a man is running down a hill with a gun",
    "592": "a man is running around a pile of dirt",
    "593": "a man is standing on a pile of dirt",
    "594": "a man is standing on a hill with a gun",
    "595": "a man is throwing a frisbee in a pile of dirt",
    "596": "a man is running up a hill with a horse",
    "597": "a man and a woman are running through a pile of dirt",
    "598": "two people are running through a pile of dirt",
    "599": "a man is riding a motorcycle on a dirt hill",
    "600": "a group of people riding motorcycles on a dirt hill",
    "601": "a dirt road with a large pile of dirt",
    "602": "a dirt road with a large pile of dirt",
    "603": "a dirt road with a large pile of dirt",
    "604": "a dirt road with a dirt pile in the background",
    "605": "a dirt road with a dirt pile in the background",
    "606": "a dirt road with a large pile of dirt",
    "607": "a dirt road with a large pile of dirt",
    "608": "a dirt road with a dirt pile in the background",
    "609": "a dirt road with a large pile of dirt",
    "610": "a dirt road with a large pile of dirt",
    "611": "a dirt road with a dirt pile in the background",
    "612": "a person riding a skateboard on a dirt road",
    "613": "a person riding a skateboard on a dirt road",
    "614": "a dirt road with a large pile of dirt",
    "615": "a dirt road with a pile of dirt in the background",
    "616": "a person walking down a dirt road with a pile of dirt",
    "617": "a dirt road with a dirt pile in the background",
    "618": "a dirt road with a dirt pile in the background",
    "619": "a person riding a bike on a dirt road",
    "620": "a dirt road with a dirt pile in the background",
    "621": "a dirt road with a dirt pile in the background",
    "622": "a dirt road with a dirt pile in the background",
    "623": "a dirt road with a dirt pile in the background",
    "624": "a dirt road with a dirt pile in the middle",
    "625": "a dirt road with a dirt pile in the background",
    "626": "a dirt road with a dirt pile in the background",
    "627": "a dirt road with a dirt pile in the background",
    "628": "a dirt road with a dirt pile in the background",
    "629": "a person is walking down a dirt road with a fire going",
    "630": "a dirt road with a dirt pile in the background",
    "631": "a fire truck is driving down a dirt road",
    "632": "a dirt road with a dirt pile in the background",
    "633": "a truck driving down a dirt road with a fire",
    "634": "a soldier is holding a gun in a movie",
    "635": "a soldier is shooting a gun in a movie",
    "636": "a soldier is kneeling down next to a wall",
    "637": "a soldier is holding a gun in a movie",
    "638": "a soldier is kneeling down in front of a wall",
    "639": "a soldier is holding a gun in a movie",
    "640": "a soldier is kneeling down in front of a wall",
    "641": "a soldier is holding a gun in a movie",
    "642": "a soldier is holding a gun in a movie",
    "643": "a soldier is holding a gun in a movie scene",
    "644": "a soldier is shooting a gun at a wall",
    "645": "a soldier is holding a gun in a movie scene",
    "646": "a soldier is holding a machine gun in front of a wall",
    "647": "a man in a military uniform with a gun",
    "648": "a soldier is running with a rifle in front of a car",
    "649": "a soldier is holding a machine gun in front of a car",
    "650": "a soldier is holding a gun in a city",
    "651": "a soldier in a military uniform holding a machine gun",
    "652": "a man in a military uniform riding a motorcycle",
    "653": "a man on a motorcycle with a gun",
    "654": "a group of soldiers are riding motorcycles near a wall",
    "655": "a group of soldiers are riding motorcycles near a wall",
    "656": "a group of soldiers are fighting in a building",
    "657": "a group of soldiers are riding motorcycles near a wall",
    "658": "a blurry picture of a man riding a motorcycle",
    "659": "a blurry image of two soldiers in uniform",
    "660": "a blurry image of two soldiers in uniform",
    "661": "a blurry image of a group of soldiers",
    "662": "a blurry image of a group of soldiers",
    "663": "a blurry image of a group of soldiers",
    "664": "a group of soldiers are looking at a cell phone",
    "665": "a man in a military uniform is holding a gun",
    "666": "a man in a military uniform is running away from a wall",
    "667": "a man in a military uniform is running away from a wall",
    "668": "a man riding a motorcycle with a helmet on",
    "669": "a blurry image of two men riding motorcycles",
    "670": "a blurry image of a man riding a horse",
    "671": "a blurry image of a man in a military uniform",
    "672": "a man in a military uniform is being attacked by another man",
    "673": "a man in a military uniform is laying down",
    "674": "a man in a military uniform is laying on a wall",
    "675": "a couple of soldiers are laying down in a room",
    "676": "a group of soldiers are sitting in a room",
    "677": "a man in a military uniform is laying down",
    "678": "a man in a military uniform is laying on the ground",
    "679": "a man in a military uniform is laying on a wall",
    "680": "a man in a military uniform is laying on a wall",
    "681": "a man in a military uniform is holding a gun",
    "682": "a man in a military uniform is holding a grenade",
    "683": "a man in a military uniform is yelling at a wall",
    "684": "a man in a military uniform is holding a gun",
    "685": "a man in a helmet is holding a gun",
    "686": "a man in a military uniform is holding a gun",
    "687": "a soldier in a helmet is laying on a wall",
    "688": "a man in a military uniform is laying down",
    "689": "a man in a military uniform is laying on the ground",
    "690": "a blurry image of a man in a military uniform",
    "691": "a blurry image of a man in a military uniform",
    "692": "a man in a military uniform is riding a motorcycle",
    "693": "a man in a military uniform is laying down",
    "694": "a man in a military uniform is looking at a wall",
    "695": "a man in a helmet is holding a cigarette",
    "696": "a man in a helmet holding a gun",
    "697": "a soldier is laying down on a wall",
    "698": "a man in a military uniform is laying on a wall",
    "699": "a man in a military uniform is laying down",
    "700": "a man in a military uniform is laying down",
    "701": "a man in a military uniform is laying on the ground",
    "702": "a blurry image of a man in a military uniform",
    "703": "a man in a military uniform is laying on a ground",
    "704": "a man in a military uniform is laying on a wall",
    "705": "a man in a military uniform is being pushed down",
    "706": "a man is laying down with a soldier on his back",
    "707": "a man in a military uniform is being held by another man",
    "708": "a man in a military uniform is being helped by another man",
    "709": "a soldier is hugging another soldier in a military uniform",
    "710": "a man in a military uniform is hugging another man",
    "711": "a soldier is holding another soldier while they are fighting",
    "712": "a man in a military uniform is laying on a wall",
    "713": "a man in a military uniform is holding a gun",
    "714": "a man is laying down with a gun in his hand",
    "715": "a man is laying down with a rifle",
    "716": "a man is laying down with a rifle",
    "717": "a group of soldiers are laying down on a wall",
    "718": "a man is laying on a wall with a gun",
    "719": "a man is holding a piece of cloth while another man is holding a gun",
    "720": "a man is laying down with a rifle",
    "721": "a man is laying down with a gun in his hand",
    "722": "a man is being held down by another man",
    "723": "a man is being held down by a soldier",
    "724": "a soldier is holding a man while another man is holding a gun",
    "725": "a soldier is holding a gun while another man is laying down",
    "726": "a soldier is holding a man down while another man is holding a gun",
    "727": "a man is holding a gun while another man is holding a bag",
    "728": "a man is holding a gun while another man is holding a gun",
    "729": "a man is laying down with a gun in his hand",
    "730": "a man is laying down with a rifle",
    "731": "a man is laying down with a gun in his hand",
    "732": "a man is holding a soldier in a military uniform",
    "733": "a man is being held down by another man",
    "734": "a man is laying down with a gun",
    "735": "a man is laying on the ground with a gun",
    "736": "a man is laying down with a gun in his hand",
    "737": "a soldier is laying down with a gun",
    "738": "a man is lying down with a gun in his hand",
    "739": "a blurry image of a man with a gun",
    "740": "a blurry image of a man with a gun",
    "741": "a blurry image of a man with a gun",
    "742": "a blurry image of a man holding a gun",
    "743": "a blurry image of a man holding a gun",
    "744": "a man holding a gun while laying on a wall",
    "745": "a soldier holding a gun while another man is lying down",
    "746": "a soldier holding a gun while a man is laying down",
    "747": "a soldier is holding a gun while another man is laying down",
    "748": "a soldier holding a gun while a man is laying down",
    "749": "a soldier holding a gun while laying on a wall",
    "750": "a soldier holding a gun while a man is laying down",
    "751": "a soldier holding a gun while a man is laying down",
    "752": "a soldier is laying down next to a wall",
    "753": "a soldier is laying down next to a wall",
    "754": "a soldier is holding a man down on a wall",
    "755": "a soldier is holding a gun while another soldier is laying down",
    "756": "a soldier is laying down next to a wall with graffiti",
    "757": "a soldier is holding a gun while another man is laying down",
    "758": "a soldier is holding a gun while another man is holding a gun",
    "759": "a soldier is laying down on a wall",
    "760": "a man in a military uniform is laying down",
    "761": "a soldier is holding a soldier's hand",
    "762": "a soldier is holding a gun while another man is holding a gun",
    "763": "a soldier is holding a gun and a soldier is holding a gun",
    "764": "a soldier is holding a rifle and a soldier is holding a gun",
    "765": "a soldier is holding a gun and a soldier is sitting next to a wall",
    "766": "a soldier is holding a rifle and a soldier is holding a gun",
    "767": "a soldier is holding a rifle while another soldier is holding a hand",
    "768": "a soldier is holding a gun while another soldier is holding a hand",
    "769": "a soldier is holding a gun and a soldier is sitting down",
    "770": "a soldier is holding a gun and a soldier is holding a hand",
    "771": "a soldier is holding a gun and a soldier is holding a gun",
    "772": "a soldier is holding a gun while another soldier is holding a hand",
    "773": "a soldier is holding a gun while laying on a wall",
    "774": "a soldier is holding a gun while another soldier is holding a hand",
    "775": "a man holding a rifle and aiming it",
    "776": "a man with a rifle is holding it",
    "777": "a man with a rifle is holding it",
    "778": "a man with a rifle is holding it up to the camera",
    "779": "a man holding a rifle and aiming it at a target",
    "780": "a man holding a rifle and another man holding a gun",
    "781": "a man holding a gun with another man",
    "782": "a man holding a gun while another man is holding a gun",
    "783": "a man holding a gun with other men",
    "784": "a man holding a bunch of guns",
    "785": "a man holding a bunch of guns in his hands",
    "786": "a man holding a gun with another man",
    "787": "a man holding a gun with another man",
    "788": "a man holding a gun with other men",
    "789": "a man holding a gun with another man",
    "790": "a man holding a gun with a smile on his face",
    "791": "a man holding a gun with other weapons",
    "792": "a man holding a gun with other people around him",
    "793": "a man holding a gun with a smile on his face",
    "794": "a man holding a gun with other people around him",
    "795": "a man holding a gun with other people around him",
    "796": "a man holding a gun with a smile on his face",
    "797": "a man holding a gun with a smile on his face",
    "798": "a man holding a gun with a smile on his face",
    "799": "a man holding a bunch of guns in his hands",
    "800": "a man holding a bunch of guns in his hands",
    "801": "a man holding a bunch of guns in his hands",
    "802": "a man holding a gun and smiling",
    "803": "a man holding a gun and smiling",
    "804": "a man holding a gun with a smile on his face",
    "805": "a man holding a gun and smiling",
    "806": "a man holding a gun and smiling",
    "807": "a man holding a gun and smiling",
    "808": "a man holding a gun with a smile on his face",
    "809": "a man holding a bunch of guns in his hands",
    "810": "a man holding a gun with a smile on his face",
    "811": "a man holding a bunch of guns in his hands",
    "812": "a man holding a gun with other people around him",
    "813": "a man holding a gun with other people around him",
    "814": "a man holding a gun with other soldiers",
    "815": "a man holding a gun with other people around him",
    "816": "a man holding a gun with other soldiers",
    "817": "a man holding a gun with other soldiers",
    "818": "a man holding a gun with other soldiers",
    "819": "a man holding a gun with other people around him",
    "820": "a man holding a gun with other weapons",
    "821": "a man holding a gun with other weapons",
    "822": "a man holding a gun with other people around him",
    "823": "a man holding a gun with other people around him",
    "824": "a man holding a gun with other people around him",
    "825": "a man with a rifle is holding a rifle",
    "826": "a group of soldiers with guns in their hands",
    "827": "a group of soldiers with guns in their hands",
    "828": "a group of soldiers with guns in their hands",
    "829": "a group of soldiers with guns in their hands",
    "830": "a man with a rifle is holding it up to a group of soldiers",
    "831": "a group of soldiers with guns in their hands",
    "832": "a group of soldiers with guns in their hands",
    "833": "a man with a rifle is holding it up to the camera",
    "834": "a group of soldiers with guns in their hands",
    "835": "a group of soldiers with guns in their hands",
    "836": "a man with a rifle is holding it up to the camera",
    "837": "a man with a rifle is holding it up to the camera",
    "838": "a man with a rifle is holding it up to the camera",
    "839": "a group of soldiers with guns in their hands",
    "840": "a soldier in a military uniform is looking at a wall",
    "841": "a soldier in a military vehicle looking at a wall",
    "842": "a soldier in a military uniform is looking at a wall",
    "843": "a soldier in a military uniform is looking at a wall",
    "844": "a soldier in a helmet and helmet is looking at a wall",
    "845": "a soldier in a helmet and helmet is looking at a wall",
    "846": "a soldier in a military uniform is driving a car",
    "847": "a soldier in a military uniform is driving a car",
    "848": "a soldier in a military uniform is driving a car",
    "849": "a soldier in a military uniform is looking at a wall",
    "850": "a soldier in a military uniform is looking at a wall",
    "851": "a soldier in a military uniform is looking at a wall",
    "852": "a soldier in a military vehicle with a gun",
    "853": "a soldier in a military vehicle with a gun",
    "854": "a soldier in a military uniform is driving a car",
    "855": "a soldier in a military uniform is driving a car",
    "856": "a soldier in a military uniform is driving a vehicle",
    "857": "a soldier in a helmet and helmet is looking at a wall",
    "858": "a soldier in a military uniform is driving a vehicle",
    "859": "a soldier in a helmet and a helmet",
    "860": "a soldier in a helmet and a helmet",
    "861": "a soldier in a helmet and a helmet",
    "862": "a soldier in a helmet and helmet is looking at a wall",
    "863": "a soldier in a helmet and helmet is looking at a wall",
    "864": "a soldier in a helmet and helmet is looking at a wall",
    "865": "a soldier in a helmet and helmet is looking at a wall",
    "866": "a soldier in a helmet and helmet is looking at a wall",
    "867": "a soldier in a helmet and helmet is looking at a wall",
    "868": "a soldier in a helmet and a helmet",
    "869": "a soldier in a helmet and a gun",
    "870": "a soldier in a helmet and a gun",
    "871": "a soldier in a helmet and a gun",
    "872": "a soldier in a helmet and helmet looking at a wall",
    "873": "a soldier in a military uniform is looking at a wall",
    "874": "a soldier is looking at a wall with a gun",
    "875": "a man holding a gun in his face",
    "876": "a man holding a gun in his hand",
    "877": "a man holding a gun in his hand",
    "878": "a man holding a gun in his hand",
    "879": "a man holding a gun in his hand",
    "880": "a man holding a gun in his hand",
    "881": "a man holding a gun in his hand",
    "882": "a man holding a gun in his hand",
    "883": "a man with a gun is looking at the camera",
    "884": "a man is holding a gun in his hand",
    "885": "a man is holding a gun in his hand",
    "886": "a man holding a gun in his hand",
    "887": "a man holding a gun in his hand",
    "888": "a man holding a gun in his hand",
    "889": "a man holding a gun in his hand",
    "890": "a man holding a gun in his hand",
    "891": "a man holding a gun in his hand",
    "892": "a man holding a gun in his hand",
    "893": "a man holding a gun in his hand",
    "894": "a man holding a gun in his hand",
    "895": "a man holding a gun in his hand",
    "896": "a man holding a gun in his hand",
    "897": "a man holding a gun in his hand",
    "898": "a man holding a gun in his hand",
    "899": "a man holding a gun in his hand",
    "900": "a man holding a gun in his hand",
    "901": "a man holding a gun in his hand",
    "902": "a man holding a gun in his hand",
    "903": "a man holding a gun in his hand",
    "904": "a man holding a gun in his hand",
    "905": "a man holding a gun in his hand",
    "906": "a man holding a gun in his hand",
    "907": "a man holding a gun in his hand",
    "908": "a man holding a gun in his hand",
    "909": "a man holding a gun in his hand",
    "910": "a man holding a gun in his hand",
    "911": "a man holding a gun in his hand",
    "912": "a man holding a gun in his hand",
    "913": "a man holding a gun in his hand",
    "914": "a man holding a gun in his hand",
    "915": "a man holding a gun in his hand",
    "916": "a man holding a gun in his hand",
    "917": "a man holding a gun in his hand",
    "918": "a man holding a gun in his hand",
    "919": "a man holding a gun in his hand",
    "920": "a man is holding a gun in his hand",
    "921": "a man is holding a gun in his hand",
    "922": "a man is holding a gun in his hand",
    "923": "a man with a gun is looking at a camera",
    "924": "a man holding a gun in his hand",
    "925": "a man holding a gun in his hand",
    "926": "a man in a helmet is looking at a gun",
    "927": "a man is holding a gun in his hand",
    "928": "a man in a helmet is looking at a gun",
    "929": "a man is holding a gun and looking at it",
    "930": "a man holding a gun in his hand",
    "931": "a man holding a gun in his hand",
    "932": "a man holding a gun in his hand",
    "933": "a man is holding a gun in his hand",
    "934": "a man holding a gun in his hand",
    "935": "a man holding a gun in his hand",
    "936": "a man holding a gun in his hand",
    "937": "a man holding a gun in his hand",
    "938": "a man holding a gun in his hand",
    "939": "a man holding a gun in his hand",
    "940": "a man is holding a gun in his hand",
    "941": "a soldier in a military uniform is holding a gun",
    "942": "a soldier in a military uniform is holding a gun",
    "943": "a soldier in a military uniform is talking on a phone",
    "944": "a soldier is talking to a camera while driving a car",
    "945": "a soldier in a military uniform is driving a car",
    "946": "a soldier is driving a car with a visor on",
    "947": "a soldier is driving a car with a helmet on",
    "948": "a soldier in a military uniform is driving a car",
    "949": "a soldier in a military uniform is driving a car",
    "950": "a soldier in a military uniform is looking at a camera",
    "951": "a soldier in a military uniform is looking at something",
    "952": "a soldier in a military uniform is looking at something",
    "953": "a soldier in a military uniform is talking on his phone",
    "954": "a soldier in a military uniform is looking at a wall",
    "955": "a soldier in a military uniform is driving a vehicle",
    "956": "a soldier in a military uniform is driving a vehicle",
    "957": "a soldier in a military uniform is looking at something",
    "958": "a soldier in a military uniform is looking at something",
    "959": "a soldier in a military uniform is looking at something",
    "960": "a soldier in a military uniform is talking to a camera",
    "961": "a soldier in a military uniform is looking at a wall",
    "962": "a soldier in a military uniform is looking at a wall",
    "963": "a soldier in a military uniform is talking on a phone",
    "964": "a soldier in a military uniform is looking at a wall",
    "965": "a soldier in a military uniform is talking on a cell phone",
    "966": "a man holding a gun with another man holding a gun",
    "967": "a man holding a gun with another man",
    "968": "a man holding two guns in his hands",
    "969": "a man holding a gun with a helmet on",
    "970": "a man with a gun in his hand",
    "971": "a man with a gun in his hand",
    "972": "a man with a gun in his hand",
    "973": "a man with a gun and a helmet",
    "974": "a man with a rifle and a gun in his mouth",
    "975": "a man with a rifle in his mouth",
    "976": "a man with a rifle and a helmet",
    "977": "a man with a rifle and a helmet",
    "978": "a man holding a gun with another man behind him",
    "979": "a man with a gun is holding it",
    "980": "a man is holding a gun while another man is holding a gun",
    "981": "a man is holding a gun while riding a motorcycle",
    "982": "a man is holding a gun while another man is holding a gun",
    "983": "a man is holding a gun in his hand",
    "984": "a person holding a gun in their hand",
    "985": "a man holding a gun in his hand",
    "986": "a soldier is holding a gun and looking at it",
    "987": "a man in a military uniform is holding a gun",
    "988": "a man in a military uniform is holding a gun",
    "989": "a man in a military uniform is holding a gun",
    "990": "a soldier is holding a rifle and aiming it",
    "991": "a soldier is holding a rifle and aiming it",
    "992": "a man in a military uniform is holding a gun",
    "993": "a man in a military uniform is holding a gun",
    "994": "a soldier is holding a rifle and aiming it",
    "995": "a man in a military uniform is holding a gun",
    "996": "a man in a military uniform is holding a rifle",
    "997": "a man in a military uniform is holding a gun",
    "998": "a soldier is holding a gun and looking at it",
    "999": "a soldier is holding a gun and looking at it",
    "1000": "a soldier is holding a gun and is looking at something",
    "1001": "a soldier in a helmet is holding a gun",
    "1002": "a soldier is holding a gun in front of a wall",
    "1003": "a soldier is holding a gun in front of a wall",
    "1004": "a soldier in a helmet and a gun is looking at a wall",
    "1005": "a soldier in a helmet and a gun is looking at a wall",
    "1006": "a man in a helmet and a gun is looking at a wall",
    "1007": "a man in a military uniform is holding a gun",
    "1008": "a man in a military uniform is holding a gun",
    "1009": "a man with a gun is looking at a wall",
    "1010": "a man with a gun is holding it in front of a wall",
    "1011": "a person holding a gun in front of a graffiti wall",
    "1012": "a person holding a gun in front of a graffiti wall",
    "1013": "a man holding a gun in front of a graffiti wall",
    "1014": "a man holding a gun in front of a wall",
    "1015": "a group of soldiers are running down a street",
    "1016": "a group of soldiers are running down a street",
    "1017": "a group of soldiers are running down a street",
    "1018": "a group of soldiers are running down a street",
    "1019": "a group of soldiers are running down a street",
    "1020": "a group of soldiers in a movie with guns",
    "1021": "a group of soldiers are running through a city",
    "1022": "a group of soldiers in a movie with guns",
    "1023": "a group of soldiers are running through a city",
    "1024": "a group of soldiers are running through a city",
    "1025": "a group of soldiers are running in a video game",
    "1026": "a group of soldiers are running through a city",
    "1027": "a group of soldiers are running through a city",
    "1028": "a group of soldiers are running through a city",
    "1029": "a group of soldiers are running in the desert",
    "1030": "a group of soldiers are running through a desert",
    "1031": "a group of soldiers are running through a desert",
    "1032": "a group of soldiers are running through a city",
    "1033": "a group of soldiers are running through a city",
    "1034": "a group of soldiers are walking down a street",
    "1035": "a group of soldiers are running through a dirt street",
    "1036": "a group of soldiers are running in a dirt field",
    "1037": "a group of soldiers are running through a desert",
    "1038": "a group of soldiers are running through a desert",
    "1039": "a view of a dirt field with a few huts",
    "1040": "a view of a dirt field with people walking around",
    "1041": "a view of a dirt field with a few huts",
    "1042": "a view of a dirt field with a few tents",
    "1043": "a view of a dirt field with a few huts",
    "1044": "a view of a dirt field with a dog looking down",
    "1045": "a view of a dirt field with a dog looking down",
    "1046": "a view of a dirt field with people walking around",
    "1047": "a view of a building with a gunshot coming out of it",
    "1048": "a view of a dirt field with people walking around",
    "1049": "a view of a dirt field with people walking around",
    "1050": "a view of a dirt field with people walking around",
    "1051": "a view of a dirt field with people and a dirt road",
    "1052": "a view of a dirt field with a few tents",
    "1053": "a view of a dirt field with people walking around",
    "1054": "a view of a dirt field with a few tents",
    "1055": "a view of a dirt field with a few people walking around",
    "1056": "a view of a dirt field with a few huts",
    "1057": "a view of a dirt field with a few huts",
    "1058": "a view of a dirt field with a few huts",
    "1059": "a view of a dirt field with a few huts",
    "1060": "a view of a dirt field with people walking around",
    "1061": "a view of a dirt field with people walking around",
    "1062": "a view of a dirt field with people walking around",
    "1063": "a view of a dirt field with people walking around",
    "1064": "a view of a dirt field with people walking around",
    "1065": "a view of a building with a gun pointing at a building",
    "1066": "a view of a building with a gun pointing at a building",
    "1067": "a view of a dirt field with people walking around",
    "1068": "a view of a dirt field with a few tents",
    "1069": "a view of a dirt field with people walking around",
    "1070": "a view of a dirt field with people walking around",
    "1071": "a group of people running down a dirt road",
    "1072": "a group of soldiers running down a dirt road",
    "1073": "a group of soldiers running down a dirt road",
    "1074": "a group of soldiers running down a dirt road",
    "1075": "a group of soldiers walking down a dirt road",
    "1076": "a group of soldiers walking down a dirt road",
    "1077": "a group of soldiers are running down a dirt road",
    "1078": "a group of soldiers running down a dirt road",
    "1079": "a man is walking down a dirt road with a gun",
    "1080": "a man is running down a dirt road with a gun",
    "1081": "a man is running down a dirt road with a gun",
    "1082": "a man is running down a dirt road with a gun",
    "1083": "a man running down a dirt road with a gun",
    "1084": "a man running down a dirt road with a gun",
    "1085": "a group of men running down a dirt road",
    "1086": "a group of people running down a dirt road",
    "1087": "a man with a backpack is walking down a street",
    "1088": "a man with a backpack is running down a street",
    "1089": "a group of men are walking down a street with a pile of rubble",
    "1090": "a man is climbing up a pile of rubble",
    "1091": "a group of men are walking down a street with a gun",
    "1092": "a group of men are walking down a dirt road",
    "1093": "a group of people walking down a dirt road",
    "1094": "a group of people walking down a dirt road",
    "1095": "a group of people walking down a dirt road",
    "1096": "a group of people walking down a dirt road",
    "1097": "a group of soldiers walking down a dirt road",
    "1098": "a group of soldiers walking down a dirt road",
    "1099": "a group of soldiers are running down a dirt road",
    "1100": "a group of soldiers are walking down a dirt road",
    "1101": "a group of people walking down a dirt road",
    "1102": "a window with a hole in it and a person looking out",
    "1103": "a window with a hole in it and a person in it",
    "1104": "a man is looking out of a window in a building",
    "1105": "a man is looking out of a window in a building",
    "1106": "a man is looking out of a window in a building",
    "1107": "a man is looking out of a window in a building",
    "1108": "a window with a hole in it and a person in it",
    "1109": "a window with a hole in it and a person looking out",
    "1110": "a man is looking out of a window in a building",
    "1111": "a man is looking out of a window in a building",
    "1112": "a person is peeking out of a window in a building",
    "1113": "a man is looking out of a window in a building",
    "1114": "a person is looking out of a window in a building",
    "1115": "a window with a hole in it and a person in it",
    "1116": "a man is looking out of a window in a building",
    "1117": "a man is looking out of a window in a building",
    "1118": "a person is looking out of a window in a building",
    "1119": "a person is peeking out of a window in a building",
    "1120": "a person is peeking out of a window in a building",
    "1121": "a person is looking out of a window in a building",
    "1122": "a person is peeking out of a window in a building",
    "1123": "a person is peeking out of a window in a building",
    "1124": "a person is looking out of a window in a building",
    "1125": "a window with a hole in it and a cat in it",
    "1126": "a man in a military uniform running through a crowd of people",
    "1127": "a man running through a crowd of people",
    "1128": "a man running through a crowd of soldiers",
    "1129": "a man running through a crowd of people",
    "1130": "a man with a rifle is running through a crowd of people",
    "1131": "a man running through a crowd of people",
    "1132": "a man running down a dirt road with a backpack",
    "1133": "a man in a military uniform walking down a dirt road",
    "1134": "a man running through a crowd of people",
    "1135": "a man running through a crowd of people",
    "1136": "a man walking down a street with a gun",
    "1137": "a man with a gun walking next to a wall",
    "1138": "a man with a gun walking next to a wall",
    "1139": "a man in a military uniform walking through a crowd of people",
    "1140": "a man in a military uniform running through a crowd",
    "1141": "a man is standing on top of a pile of rocks",
    "1142": "a man is standing next to a wall with a gun",
    "1143": "a man is running up a hill in a movie",
    "1144": "a man is climbing over a wall of bricks",
    "1145": "a man is standing on a pile of rocks",
    "1146": "a man is running up a wall with a backpack",
    "1147": "a man in a military uniform is walking through a crowd of people",
    "1148": "a man is reaching out to a group of people",
    "1149": "a group of soldiers are standing on top of a wall",
    "1150": "a group of soldiers are climbing a wall",
    "1151": "a group of soldiers are climbing a wall",
    "1152": "a group of soldiers are standing on top of a building",
    "1153": "a group of soldiers are standing on top of a building",
    "1154": "a group of soldiers standing in a field",
    "1155": "a group of soldiers standing on top of a building",
    "1156": "a group of soldiers are standing on top of a building",
    "1157": "a group of soldiers are standing on top of a building",
    "1158": "a group of soldiers are standing on top of a building",
    "1159": "a group of soldiers are standing on top of a building",
    "1160": "a man in a military uniform is walking through a crowd",
    "1161": "a man with a gun is walking through a crowd of people",
    "1162": "a man with a gun is walking through a city",
    "1163": "a man with a gun is walking down a hill",
    "1164": "a man with a gun is walking through a city",
    "1165": "a man with a gun is standing in a crowd",
    "1166": "a silhouette of a man with a gun in the fog",
    "1167": "a silhouette of a man with a gun on his shoulder",
    "1168": "a man is standing in the fog with a gun",
    "1169": "a man is standing in the middle of a crowd",
    "1170": "a man is standing on top of a building with a gun",
    "1171": "a man is running through a crowd of people",
    "1172": "a silhouette of a man walking down a hill",
    "1173": "a silhouette of a man with a gun in the sun",
    "1174": "a silhouette of a man with a gun on a hill",
    "1175": "a silhouette of a soldier standing on a hill",
    "1176": "a silhouette of a soldier standing on top of a hill",
    "1177": "a silhouette of a soldier with a gun on a hill",
    "1178": "a silhouette of a man holding a gun in the sun",
    "1179": "a silhouette of a man holding a rifle",
    "1180": "a silhouette of a man with a rifle in the sun",
    "1181": "a man is standing on top of a hill with a rifle",
    "1182": "a man is jumping up a hill with a rifle",
    "1183": "a man is jumping up a hill with a rifle",
    "1184": "a silhouette of a man with a rifle in his hand",
    "1185": "a silhouette of a man with a gun on top of a hill",
    "1186": "a man is standing on top of a hill with a gun",
    "1187": "a silhouette of a man with a rifle in the sun",
    "1188": "a silhouette of a man with a rifle on a hill",
    "1189": "a silhouette of a man standing on top of a hill",
    "1190": "a silhouette of a man with a rifle in the sun",
    "1191": "a silhouette of a man with a rifle in the fog",
    "1192": "a silhouette of a man holding a rifle in the fog",
    "1193": "a silhouette of a man with a rifle in the sun",
    "1194": "a silhouette of a man with a rifle in the sun",
    "1195": "a silhouette of a man with a rifle in the sun",
    "1196": "a man in a military uniform is walking up a building",
    "1197": "a man in a military uniform walking up a building",
    "1198": "a man in a military uniform walking down a street",
    "1199": "a man in a military uniform is walking up a building",
    "1200": "a man in a military uniform is walking up a building"
}